package com.wandoujia.push2;

final class n
  implements Runnable
{
  n(PushService paramPushService, String paramString, long paramLong)
  {
  }

  // ERROR //
  public final void run()
  {
    // Byte code:
    //   0: invokestatic 39	com/wandoujia/push2/PushService:b	()Landroid/util/Pair;
    //   3: astore_1
    //   4: aload_1
    //   5: ifnonnull +16 -> 21
    //   8: aload_0
    //   9: getfield 16	com/wandoujia/push2/n:c	Lcom/wandoujia/push2/PushService;
    //   12: invokestatic 43	com/wandoujia/push2/PushService:d	(Lcom/wandoujia/push2/PushService;)Landroid/os/Handler;
    //   15: iconst_1
    //   16: invokevirtual 49	android/os/Handler:sendEmptyMessage	(I)Z
    //   19: pop
    //   20: return
    //   21: sipush 1024
    //   24: newarray byte
    //   26: astore_2
    //   27: new 51	com/squareup/wire/Wire
    //   30: dup
    //   31: iconst_0
    //   32: anewarray 53	java/lang/Class
    //   35: invokespecial 56	com/squareup/wire/Wire:<init>	([Ljava/lang/Class;)V
    //   38: astore_3
    //   39: sipush 900
    //   42: istore 4
    //   44: new 58	java/net/Socket
    //   47: dup
    //   48: aload_1
    //   49: getfield 64	android/util/Pair:first	Ljava/lang/Object;
    //   52: checkcast 66	java/lang/String
    //   55: aload_1
    //   56: getfield 69	android/util/Pair:second	Ljava/lang/Object;
    //   59: checkcast 71	java/lang/Integer
    //   62: invokevirtual 75	java/lang/Integer:intValue	()I
    //   65: invokespecial 78	java/net/Socket:<init>	(Ljava/lang/String;I)V
    //   68: astore 5
    //   70: aload 5
    //   72: getstatic 84	java/util/concurrent/TimeUnit:SECONDS	Ljava/util/concurrent/TimeUnit;
    //   75: ldc2_w 85
    //   78: invokevirtual 90	java/util/concurrent/TimeUnit:toMillis	(J)J
    //   81: l2i
    //   82: invokevirtual 94	java/net/Socket:setSoTimeout	(I)V
    //   85: new 96	java/io/DataInputStream
    //   88: dup
    //   89: new 98	java/io/BufferedInputStream
    //   92: dup
    //   93: aload 5
    //   95: invokevirtual 102	java/net/Socket:getInputStream	()Ljava/io/InputStream;
    //   98: invokespecial 105	java/io/BufferedInputStream:<init>	(Ljava/io/InputStream;)V
    //   101: invokespecial 106	java/io/DataInputStream:<init>	(Ljava/io/InputStream;)V
    //   104: astore 8
    //   106: new 108	java/io/DataOutputStream
    //   109: dup
    //   110: new 110	java/io/BufferedOutputStream
    //   113: dup
    //   114: aload 5
    //   116: invokevirtual 114	java/net/Socket:getOutputStream	()Ljava/io/OutputStream;
    //   119: invokespecial 117	java/io/BufferedOutputStream:<init>	(Ljava/io/OutputStream;)V
    //   122: invokespecial 118	java/io/DataOutputStream:<init>	(Ljava/io/OutputStream;)V
    //   125: astore 9
    //   127: aload 9
    //   129: aload_0
    //   130: getfield 18	com/wandoujia/push2/n:a	Ljava/lang/String;
    //   133: aload_0
    //   134: getfield 20	com/wandoujia/push2/n:b	J
    //   137: invokestatic 121	com/wandoujia/push2/PushService:a	(Ljava/lang/String;J)Lcom/wandoujia/push2/protocol/proto/Upload;
    //   140: invokestatic 124	com/wandoujia/push2/PushService:a	(Ljava/io/DataOutputStream;Lcom/squareup/wire/Message;)V
    //   143: aload_2
    //   144: astore 25
    //   146: aload 8
    //   148: invokevirtual 127	java/io/DataInputStream:readInt	()I
    //   151: istore 26
    //   153: aload 25
    //   155: arraylength
    //   156: iload 26
    //   158: if_icmpge +408 -> 566
    //   161: iload 26
    //   163: newarray byte
    //   165: astore 27
    //   167: aload 8
    //   169: aload 27
    //   171: iconst_0
    //   172: iload 26
    //   174: invokevirtual 131	java/io/DataInputStream:readFully	([BII)V
    //   177: aload_3
    //   178: aload 27
    //   180: iconst_0
    //   181: iload 26
    //   183: ldc 133
    //   185: invokevirtual 137	com/squareup/wire/Wire:parseFrom	([BIILjava/lang/Class;)Lcom/squareup/wire/Message;
    //   188: checkcast 133	com/wandoujia/push2/protocol/proto/Download
    //   191: astore 38
    //   193: aload 38
    //   195: astore 29
    //   197: lconst_0
    //   198: lstore 30
    //   200: aload 29
    //   202: ifnull +240 -> 442
    //   205: aload 29
    //   207: getfield 141	com/wandoujia/push2/protocol/proto/Download:messages	Ljava/util/List;
    //   210: ifnull +180 -> 390
    //   213: aload 29
    //   215: getfield 141	com/wandoujia/push2/protocol/proto/Download:messages	Ljava/util/List;
    //   218: invokeinterface 147 1 0
    //   223: ifne +167 -> 390
    //   226: new 149	com/wandoujia/push2/c
    //   229: dup
    //   230: invokespecial 150	com/wandoujia/push2/c:<init>	()V
    //   233: astore 32
    //   235: aload 32
    //   237: ldc 152
    //   239: aload 29
    //   241: getfield 141	com/wandoujia/push2/protocol/proto/Download:messages	Ljava/util/List;
    //   244: invokeinterface 155 1 0
    //   249: invokestatic 159	java/lang/String:valueOf	(I)Ljava/lang/String;
    //   252: invokevirtual 162	com/wandoujia/push2/c:a	(Ljava/lang/String;Ljava/lang/String;)Lcom/wandoujia/push2/c;
    //   255: pop
    //   256: getstatic 168	com/wandoujia/push2/LogHelper$Action:RECV_MSG_FROM_SERVER	Lcom/wandoujia/push2/LogHelper$Action;
    //   259: aload 32
    //   261: invokestatic 173	com/wandoujia/push2/LogHelper:a	(Lcom/wandoujia/push2/LogHelper$Action;Lcom/wandoujia/push2/c;)V
    //   264: aload 29
    //   266: getfield 141	com/wandoujia/push2/protocol/proto/Download:messages	Ljava/util/List;
    //   269: iconst_m1
    //   270: aload 29
    //   272: getfield 141	com/wandoujia/push2/protocol/proto/Download:messages	Ljava/util/List;
    //   275: invokeinterface 155 1 0
    //   280: iadd
    //   281: invokeinterface 177 2 0
    //   286: checkcast 179	com/wandoujia/push2/protocol/proto/Download$Msg
    //   289: getfield 183	com/wandoujia/push2/protocol/proto/Download$Msg:id	Ljava/lang/Long;
    //   292: invokevirtual 189	java/lang/Long:longValue	()J
    //   295: lstore 34
    //   297: aload 29
    //   299: getfield 141	com/wandoujia/push2/protocol/proto/Download:messages	Ljava/util/List;
    //   302: invokeinterface 193 1 0
    //   307: astore 36
    //   309: aload 36
    //   311: invokeinterface 198 1 0
    //   316: ifeq +70 -> 386
    //   319: aload 36
    //   321: invokeinterface 202 1 0
    //   326: checkcast 179	com/wandoujia/push2/protocol/proto/Download$Msg
    //   329: astore 37
    //   331: aload_0
    //   332: getfield 16	com/wandoujia/push2/n:c	Lcom/wandoujia/push2/PushService;
    //   335: aload 37
    //   337: invokestatic 205	com/wandoujia/push2/PushService:a	(Lcom/wandoujia/push2/PushService;Lcom/wandoujia/push2/protocol/proto/Download$Msg;)V
    //   340: goto -31 -> 309
    //   343: astore 22
    //   345: aload 5
    //   347: invokevirtual 208	java/net/Socket:close	()V
    //   350: aload_0
    //   351: getfield 16	com/wandoujia/push2/n:c	Lcom/wandoujia/push2/PushService;
    //   354: invokestatic 43	com/wandoujia/push2/PushService:d	(Lcom/wandoujia/push2/PushService;)Landroid/os/Handler;
    //   357: iconst_1
    //   358: invokevirtual 49	android/os/Handler:sendEmptyMessage	(I)Z
    //   361: pop
    //   362: return
    //   363: astore 6
    //   365: aload_0
    //   366: getfield 16	com/wandoujia/push2/n:c	Lcom/wandoujia/push2/PushService;
    //   369: invokestatic 43	com/wandoujia/push2/PushService:d	(Lcom/wandoujia/push2/PushService;)Landroid/os/Handler;
    //   372: iconst_1
    //   373: invokevirtual 49	android/os/Handler:sendEmptyMessage	(I)Z
    //   376: pop
    //   377: return
    //   378: astore 28
    //   380: aconst_null
    //   381: astore 29
    //   383: goto -186 -> 197
    //   386: lload 34
    //   388: lstore 30
    //   390: aload 29
    //   392: getfield 212	com/wandoujia/push2/protocol/proto/Download:conf	Lcom/wandoujia/push2/protocol/proto/Download$Conf;
    //   395: ifnull +47 -> 442
    //   398: aload 29
    //   400: getfield 212	com/wandoujia/push2/protocol/proto/Download:conf	Lcom/wandoujia/push2/protocol/proto/Download$Conf;
    //   403: getfield 218	com/wandoujia/push2/protocol/proto/Download$Conf:timeout	Ljava/lang/Integer;
    //   406: invokevirtual 75	java/lang/Integer:intValue	()I
    //   409: iload 4
    //   411: if_icmpeq +31 -> 442
    //   414: aload 29
    //   416: getfield 212	com/wandoujia/push2/protocol/proto/Download:conf	Lcom/wandoujia/push2/protocol/proto/Download$Conf;
    //   419: getfield 218	com/wandoujia/push2/protocol/proto/Download$Conf:timeout	Ljava/lang/Integer;
    //   422: invokevirtual 75	java/lang/Integer:intValue	()I
    //   425: istore 4
    //   427: aload 5
    //   429: getstatic 84	java/util/concurrent/TimeUnit:SECONDS	Ljava/util/concurrent/TimeUnit;
    //   432: iload 4
    //   434: i2l
    //   435: invokevirtual 90	java/util/concurrent/TimeUnit:toMillis	(J)J
    //   438: l2i
    //   439: invokevirtual 94	java/net/Socket:setSoTimeout	(I)V
    //   442: aload 9
    //   444: lload 30
    //   446: invokestatic 221	com/wandoujia/push2/PushService:a	(J)Lcom/wandoujia/push2/protocol/proto/Upload;
    //   449: invokestatic 124	com/wandoujia/push2/PushService:a	(Ljava/io/DataOutputStream;Lcom/squareup/wire/Message;)V
    //   452: aload 27
    //   454: astore 25
    //   456: goto -310 -> 146
    //   459: astore 19
    //   461: aload 5
    //   463: invokevirtual 208	java/net/Socket:close	()V
    //   466: aload_0
    //   467: getfield 16	com/wandoujia/push2/n:c	Lcom/wandoujia/push2/PushService;
    //   470: invokestatic 43	com/wandoujia/push2/PushService:d	(Lcom/wandoujia/push2/PushService;)Landroid/os/Handler;
    //   473: iconst_1
    //   474: invokevirtual 49	android/os/Handler:sendEmptyMessage	(I)Z
    //   477: pop
    //   478: return
    //   479: astore 16
    //   481: aload 5
    //   483: invokevirtual 208	java/net/Socket:close	()V
    //   486: aload_0
    //   487: getfield 16	com/wandoujia/push2/n:c	Lcom/wandoujia/push2/PushService;
    //   490: invokestatic 43	com/wandoujia/push2/PushService:d	(Lcom/wandoujia/push2/PushService;)Landroid/os/Handler;
    //   493: iconst_1
    //   494: invokevirtual 49	android/os/Handler:sendEmptyMessage	(I)Z
    //   497: pop
    //   498: return
    //   499: astore 13
    //   501: aload 5
    //   503: invokevirtual 208	java/net/Socket:close	()V
    //   506: aload_0
    //   507: getfield 16	com/wandoujia/push2/n:c	Lcom/wandoujia/push2/PushService;
    //   510: invokestatic 43	com/wandoujia/push2/PushService:d	(Lcom/wandoujia/push2/PushService;)Landroid/os/Handler;
    //   513: iconst_1
    //   514: invokevirtual 49	android/os/Handler:sendEmptyMessage	(I)Z
    //   517: pop
    //   518: return
    //   519: astore 10
    //   521: aload 5
    //   523: invokevirtual 208	java/net/Socket:close	()V
    //   526: aload_0
    //   527: getfield 16	com/wandoujia/push2/n:c	Lcom/wandoujia/push2/PushService;
    //   530: invokestatic 43	com/wandoujia/push2/PushService:d	(Lcom/wandoujia/push2/PushService;)Landroid/os/Handler;
    //   533: iconst_1
    //   534: invokevirtual 49	android/os/Handler:sendEmptyMessage	(I)Z
    //   537: pop
    //   538: aload 10
    //   540: athrow
    //   541: astore 23
    //   543: goto -193 -> 350
    //   546: astore 20
    //   548: goto -82 -> 466
    //   551: astore 17
    //   553: goto -67 -> 486
    //   556: astore 14
    //   558: goto -52 -> 506
    //   561: astore 11
    //   563: goto -37 -> 526
    //   566: aload 25
    //   568: astore 27
    //   570: goto -403 -> 167
    //
    // Exception table:
    //   from	to	target	type
    //   85	143	343	java/io/IOException
    //   146	167	343	java/io/IOException
    //   167	177	343	java/io/IOException
    //   177	193	343	java/io/IOException
    //   205	309	343	java/io/IOException
    //   309	340	343	java/io/IOException
    //   390	442	343	java/io/IOException
    //   442	452	343	java/io/IOException
    //   44	85	363	java/io/IOException
    //   177	193	378	java/lang/Error
    //   85	143	459	java/lang/OutOfMemoryError
    //   146	167	459	java/lang/OutOfMemoryError
    //   167	177	459	java/lang/OutOfMemoryError
    //   177	193	459	java/lang/OutOfMemoryError
    //   205	309	459	java/lang/OutOfMemoryError
    //   309	340	459	java/lang/OutOfMemoryError
    //   390	442	459	java/lang/OutOfMemoryError
    //   442	452	459	java/lang/OutOfMemoryError
    //   85	143	479	java/lang/IllegalArgumentException
    //   146	167	479	java/lang/IllegalArgumentException
    //   167	177	479	java/lang/IllegalArgumentException
    //   177	193	479	java/lang/IllegalArgumentException
    //   205	309	479	java/lang/IllegalArgumentException
    //   309	340	479	java/lang/IllegalArgumentException
    //   390	442	479	java/lang/IllegalArgumentException
    //   442	452	479	java/lang/IllegalArgumentException
    //   85	143	499	java/lang/Throwable
    //   146	167	499	java/lang/Throwable
    //   167	177	499	java/lang/Throwable
    //   177	193	499	java/lang/Throwable
    //   205	309	499	java/lang/Throwable
    //   309	340	499	java/lang/Throwable
    //   390	442	499	java/lang/Throwable
    //   442	452	499	java/lang/Throwable
    //   85	143	519	finally
    //   146	167	519	finally
    //   167	177	519	finally
    //   177	193	519	finally
    //   205	309	519	finally
    //   309	340	519	finally
    //   390	442	519	finally
    //   442	452	519	finally
    //   345	350	541	java/io/IOException
    //   461	466	546	java/io/IOException
    //   481	486	551	java/io/IOException
    //   501	506	556	java/io/IOException
    //   521	526	561	java/io/IOException
  }
}

/* Location:           C:\WorkSpace\WandDouJiaNotificationBar\WanDou1.jar
 * Qualified Name:     com.wandoujia.push2.n
 * JD-Core Version:    0.6.0
 */