package com.wandoujia.shared_storage;

final class f
  implements Runnable
{
  f(e parame)
  {
  }

  // ERROR //
  public final void run()
  {
    // Byte code:
    //   0: aload_0
    //   1: getfield 12	com/wandoujia/shared_storage/f:a	Lcom/wandoujia/shared_storage/e;
    //   4: invokestatic 25	com/wandoujia/shared_storage/e:a	(Lcom/wandoujia/shared_storage/e;)Ljava/util/HashMap;
    //   7: invokevirtual 30	java/util/HashMap:clear	()V
    //   10: new 32	com/wandoujia/gson/c
    //   13: dup
    //   14: invokespecial 33	com/wandoujia/gson/c:<init>	()V
    //   17: astore_1
    //   18: aload_0
    //   19: getfield 12	com/wandoujia/shared_storage/f:a	Lcom/wandoujia/shared_storage/e;
    //   22: invokevirtual 37	com/wandoujia/shared_storage/e:c	()Ljava/lang/reflect/Type;
    //   25: astore 5
    //   27: aload_1
    //   28: aload_0
    //   29: getfield 12	com/wandoujia/shared_storage/f:a	Lcom/wandoujia/shared_storage/e;
    //   32: invokevirtual 41	com/wandoujia/shared_storage/e:f	()Ljava/lang/String;
    //   35: aload 5
    //   37: invokevirtual 44	com/wandoujia/gson/c:a	(Ljava/lang/String;Ljava/lang/reflect/Type;)Ljava/lang/Object;
    //   40: checkcast 46	java/util/Collection
    //   43: astore 6
    //   45: aload 6
    //   47: ifnull +64 -> 111
    //   50: aload 6
    //   52: invokeinterface 50 1 0
    //   57: astore 7
    //   59: aload 7
    //   61: invokeinterface 56 1 0
    //   66: ifeq +45 -> 111
    //   69: aload 7
    //   71: invokeinterface 60 1 0
    //   76: checkcast 62	com/wandoujia/shared_storage/StorageLine
    //   79: astore 8
    //   81: aload_0
    //   82: getfield 12	com/wandoujia/shared_storage/f:a	Lcom/wandoujia/shared_storage/e;
    //   85: invokestatic 25	com/wandoujia/shared_storage/e:a	(Lcom/wandoujia/shared_storage/e;)Ljava/util/HashMap;
    //   88: aload 8
    //   90: invokevirtual 65	com/wandoujia/shared_storage/StorageLine:getKey	()Ljava/lang/String;
    //   93: aload 8
    //   95: invokevirtual 69	java/util/HashMap:put	(Ljava/lang/Object;Ljava/lang/Object;)Ljava/lang/Object;
    //   98: pop
    //   99: goto -40 -> 59
    //   102: astore 4
    //   104: aload_0
    //   105: getfield 12	com/wandoujia/shared_storage/f:a	Lcom/wandoujia/shared_storage/e;
    //   108: invokevirtual 72	com/wandoujia/shared_storage/e:g	()V
    //   111: return
    //   112: astore_3
    //   113: aload_3
    //   114: athrow
    //   115: astore_2
    //   116: return
    //
    // Exception table:
    //   from	to	target	type
    //   10	45	102	com/wandoujia/gson/JsonSyntaxException
    //   50	59	102	com/wandoujia/gson/JsonSyntaxException
    //   59	99	102	com/wandoujia/gson/JsonSyntaxException
    //   10	45	112	finally
    //   50	59	112	finally
    //   59	99	112	finally
    //   104	111	112	finally
    //   10	45	115	java/lang/Throwable
    //   50	59	115	java/lang/Throwable
    //   59	99	115	java/lang/Throwable
  }
}

/* Location:           C:\WorkSpace\WandDouJiaNotificationBar\WanDou2.jar
 * Qualified Name:     com.wandoujia.shared_storage.f
 * JD-Core Version:    0.6.0
 */