package com.wandoujia.log;

final class h
  implements Runnable
{
  private h(LogSender paramLogSender)
  {
  }

  // ERROR //
  public final void run()
  {
    // Byte code:
    //   0: aconst_null
    //   1: astore_1
    //   2: ldc2_w 28
    //   5: lstore_2
    //   6: iconst_0
    //   7: istore 4
    //   9: aconst_null
    //   10: astore 5
    //   12: new 31	java/io/ByteArrayOutputStream
    //   15: dup
    //   16: invokespecial 32	java/io/ByteArrayOutputStream:<init>	()V
    //   19: astore 6
    //   21: new 34	java/util/zip/GZIPOutputStream
    //   24: dup
    //   25: aload 6
    //   27: sipush 1024
    //   30: invokespecial 37	java/util/zip/GZIPOutputStream:<init>	(Ljava/io/OutputStream;I)V
    //   33: astore 7
    //   35: aload 7
    //   37: aload_0
    //   38: getfield 12	com/wandoujia/log/h:a	Lcom/wandoujia/log/LogSender;
    //   41: invokestatic 43	com/wandoujia/log/LogSender:access$300	(Lcom/wandoujia/log/LogSender;)Ljava/lang/String;
    //   44: invokevirtual 49	java/lang/String:getBytes	()[B
    //   47: invokevirtual 53	java/util/zip/GZIPOutputStream:write	([B)V
    //   50: aload_0
    //   51: getfield 12	com/wandoujia/log/h:a	Lcom/wandoujia/log/LogSender;
    //   54: invokestatic 57	com/wandoujia/log/LogSender:access$800	(Lcom/wandoujia/log/LogSender;)Lcom/wandoujia/log/i;
    //   57: aload 7
    //   59: invokevirtual 62	com/wandoujia/log/i:a	(Ljava/io/OutputStream;)J
    //   62: lstore_2
    //   63: aload 7
    //   65: invokevirtual 65	java/util/zip/GZIPOutputStream:finish	()V
    //   68: aload 6
    //   70: invokevirtual 68	java/io/ByteArrayOutputStream:toByteArray	()[B
    //   73: aload_0
    //   74: getfield 12	com/wandoujia/log/h:a	Lcom/wandoujia/log/LogSender;
    //   77: invokestatic 72	com/wandoujia/log/LogSender:access$900	(Lcom/wandoujia/log/LogSender;)Landroid/content/Context;
    //   80: invokestatic 78	com/wandoujia/base/utils/CipherUtil:getAESKey	(Landroid/content/Context;)[B
    //   83: invokestatic 82	com/wandoujia/base/utils/CipherUtil:encrypt	([B[B)[B
    //   86: astore 28
    //   88: new 84	org/apache/http/client/methods/HttpPost
    //   91: dup
    //   92: aload_0
    //   93: getfield 12	com/wandoujia/log/h:a	Lcom/wandoujia/log/LogSender;
    //   96: invokestatic 87	com/wandoujia/log/LogSender:access$000	(Lcom/wandoujia/log/LogSender;)Ljava/lang/String;
    //   99: invokespecial 90	org/apache/http/client/methods/HttpPost:<init>	(Ljava/lang/String;)V
    //   102: astore 29
    //   104: aload 29
    //   106: new 92	org/apache/http/entity/ByteArrayEntity
    //   109: dup
    //   110: aload 28
    //   112: invokespecial 94	org/apache/http/entity/ByteArrayEntity:<init>	([B)V
    //   115: invokevirtual 98	org/apache/http/client/methods/HttpPost:setEntity	(Lorg/apache/http/HttpEntity;)V
    //   118: aload_0
    //   119: getfield 12	com/wandoujia/log/h:a	Lcom/wandoujia/log/LogSender;
    //   122: invokestatic 102	com/wandoujia/log/LogSender:access$1000	(Lcom/wandoujia/log/LogSender;)Lorg/apache/http/client/HttpClient;
    //   125: astore 30
    //   127: iconst_0
    //   128: istore 4
    //   130: aconst_null
    //   131: astore 5
    //   133: aload 30
    //   135: ifnonnull +18 -> 153
    //   138: aload_0
    //   139: getfield 12	com/wandoujia/log/h:a	Lcom/wandoujia/log/LogSender;
    //   142: new 104	com/wandoujia/rpc/http/client/PhoenixHttpClient
    //   145: dup
    //   146: invokespecial 105	com/wandoujia/rpc/http/client/PhoenixHttpClient:<init>	()V
    //   149: invokestatic 109	com/wandoujia/log/LogSender:access$1002	(Lcom/wandoujia/log/LogSender;Lorg/apache/http/client/HttpClient;)Lorg/apache/http/client/HttpClient;
    //   152: pop
    //   153: aload_0
    //   154: getfield 12	com/wandoujia/log/h:a	Lcom/wandoujia/log/LogSender;
    //   157: invokestatic 102	com/wandoujia/log/LogSender:access$1000	(Lcom/wandoujia/log/LogSender;)Lorg/apache/http/client/HttpClient;
    //   160: aload 29
    //   162: invokeinterface 115 2 0
    //   167: astore 32
    //   169: aload 32
    //   171: invokeinterface 121 1 0
    //   176: astore 33
    //   178: aload 33
    //   180: astore 5
    //   182: aload 32
    //   184: invokeinterface 125 1 0
    //   189: invokeinterface 131 1 0
    //   194: istore 36
    //   196: iconst_0
    //   197: istore 4
    //   199: iload 36
    //   201: sipush 200
    //   204: if_icmpne +44 -> 248
    //   207: iconst_1
    //   208: istore 4
    //   210: aload_0
    //   211: getfield 12	com/wandoujia/log/h:a	Lcom/wandoujia/log/LogSender;
    //   214: invokestatic 72	com/wandoujia/log/LogSender:access$900	(Lcom/wandoujia/log/LogSender;)Landroid/content/Context;
    //   217: ldc 133
    //   219: iconst_0
    //   220: invokevirtual 139	android/content/Context:getSharedPreferences	(Ljava/lang/String;I)Landroid/content/SharedPreferences;
    //   223: invokeinterface 145 1 0
    //   228: astore 38
    //   230: aload 38
    //   232: ldc 147
    //   234: invokestatic 153	java/lang/System:currentTimeMillis	()J
    //   237: invokeinterface 159 4 0
    //   242: pop
    //   243: aload 38
    //   245: invokestatic 165	com/wandoujia/base/utils/SharePrefSubmitor:submit	(Landroid/content/SharedPreferences$Editor;)V
    //   248: aload 7
    //   250: invokestatic 171	com/wandoujia/base/utils/IOUtils:close	(Ljava/io/Closeable;)V
    //   253: aload 6
    //   255: invokestatic 171	com/wandoujia/base/utils/IOUtils:close	(Ljava/io/Closeable;)V
    //   258: lload_2
    //   259: lconst_0
    //   260: lcmp
    //   261: ifle +19 -> 280
    //   264: iload 4
    //   266: ifeq +27 -> 293
    //   269: aload_0
    //   270: getfield 12	com/wandoujia/log/h:a	Lcom/wandoujia/log/LogSender;
    //   273: invokestatic 57	com/wandoujia/log/LogSender:access$800	(Lcom/wandoujia/log/LogSender;)Lcom/wandoujia/log/i;
    //   276: lload_2
    //   277: invokevirtual 174	com/wandoujia/log/i:a	(J)V
    //   280: aload 5
    //   282: ifnull +10 -> 292
    //   285: aload 5
    //   287: invokeinterface 179 1 0
    //   292: return
    //   293: aload_0
    //   294: getfield 12	com/wandoujia/log/h:a	Lcom/wandoujia/log/LogSender;
    //   297: invokestatic 57	com/wandoujia/log/LogSender:access$800	(Lcom/wandoujia/log/LogSender;)Lcom/wandoujia/log/i;
    //   300: lload_2
    //   301: invokevirtual 182	com/wandoujia/log/i:b	(J)V
    //   304: goto -24 -> 280
    //   307: astore 53
    //   309: aconst_null
    //   310: astore 6
    //   312: aconst_null
    //   313: astore 7
    //   315: iconst_0
    //   316: istore 10
    //   318: aconst_null
    //   319: astore 9
    //   321: aload 7
    //   323: invokestatic 171	com/wandoujia/base/utils/IOUtils:close	(Ljava/io/Closeable;)V
    //   326: aload 6
    //   328: invokestatic 171	com/wandoujia/base/utils/IOUtils:close	(Ljava/io/Closeable;)V
    //   331: lload_2
    //   332: lconst_0
    //   333: lcmp
    //   334: ifle +19 -> 353
    //   337: iload 10
    //   339: ifeq +30 -> 369
    //   342: aload_0
    //   343: getfield 12	com/wandoujia/log/h:a	Lcom/wandoujia/log/LogSender;
    //   346: invokestatic 57	com/wandoujia/log/LogSender:access$800	(Lcom/wandoujia/log/LogSender;)Lcom/wandoujia/log/i;
    //   349: lload_2
    //   350: invokevirtual 174	com/wandoujia/log/i:a	(J)V
    //   353: aload 9
    //   355: ifnull -63 -> 292
    //   358: aload 9
    //   360: invokeinterface 179 1 0
    //   365: return
    //   366: astore 11
    //   368: return
    //   369: aload_0
    //   370: getfield 12	com/wandoujia/log/h:a	Lcom/wandoujia/log/LogSender;
    //   373: invokestatic 57	com/wandoujia/log/LogSender:access$800	(Lcom/wandoujia/log/LogSender;)Lcom/wandoujia/log/i;
    //   376: lload_2
    //   377: invokevirtual 182	com/wandoujia/log/i:b	(J)V
    //   380: goto -27 -> 353
    //   383: astore 52
    //   385: aconst_null
    //   386: astore 6
    //   388: aconst_null
    //   389: astore 7
    //   391: aload 7
    //   393: invokestatic 171	com/wandoujia/base/utils/IOUtils:close	(Ljava/io/Closeable;)V
    //   396: aload 6
    //   398: invokestatic 171	com/wandoujia/base/utils/IOUtils:close	(Ljava/io/Closeable;)V
    //   401: lload_2
    //   402: lconst_0
    //   403: lcmp
    //   404: ifle +19 -> 423
    //   407: iload 4
    //   409: ifeq +30 -> 439
    //   412: aload_0
    //   413: getfield 12	com/wandoujia/log/h:a	Lcom/wandoujia/log/LogSender;
    //   416: invokestatic 57	com/wandoujia/log/LogSender:access$800	(Lcom/wandoujia/log/LogSender;)Lcom/wandoujia/log/i;
    //   419: lload_2
    //   420: invokevirtual 174	com/wandoujia/log/i:a	(J)V
    //   423: aload 5
    //   425: ifnull -133 -> 292
    //   428: aload 5
    //   430: invokeinterface 179 1 0
    //   435: return
    //   436: astore 13
    //   438: return
    //   439: aload_0
    //   440: getfield 12	com/wandoujia/log/h:a	Lcom/wandoujia/log/LogSender;
    //   443: invokestatic 57	com/wandoujia/log/LogSender:access$800	(Lcom/wandoujia/log/LogSender;)Lcom/wandoujia/log/i;
    //   446: lload_2
    //   447: invokevirtual 182	com/wandoujia/log/i:b	(J)V
    //   450: goto -27 -> 423
    //   453: astore 51
    //   455: aconst_null
    //   456: astore 6
    //   458: aconst_null
    //   459: astore 7
    //   461: aload 7
    //   463: invokestatic 171	com/wandoujia/base/utils/IOUtils:close	(Ljava/io/Closeable;)V
    //   466: aload 6
    //   468: invokestatic 171	com/wandoujia/base/utils/IOUtils:close	(Ljava/io/Closeable;)V
    //   471: lload_2
    //   472: lconst_0
    //   473: lcmp
    //   474: ifle +19 -> 493
    //   477: iload 4
    //   479: ifeq +30 -> 509
    //   482: aload_0
    //   483: getfield 12	com/wandoujia/log/h:a	Lcom/wandoujia/log/LogSender;
    //   486: invokestatic 57	com/wandoujia/log/LogSender:access$800	(Lcom/wandoujia/log/LogSender;)Lcom/wandoujia/log/i;
    //   489: lload_2
    //   490: invokevirtual 174	com/wandoujia/log/i:a	(J)V
    //   493: aload 5
    //   495: ifnull -203 -> 292
    //   498: aload 5
    //   500: invokeinterface 179 1 0
    //   505: return
    //   506: astore 15
    //   508: return
    //   509: aload_0
    //   510: getfield 12	com/wandoujia/log/h:a	Lcom/wandoujia/log/LogSender;
    //   513: invokestatic 57	com/wandoujia/log/LogSender:access$800	(Lcom/wandoujia/log/LogSender;)Lcom/wandoujia/log/i;
    //   516: lload_2
    //   517: invokevirtual 182	com/wandoujia/log/i:b	(J)V
    //   520: goto -27 -> 493
    //   523: astore 50
    //   525: aconst_null
    //   526: astore 6
    //   528: aconst_null
    //   529: astore 7
    //   531: aload 7
    //   533: invokestatic 171	com/wandoujia/base/utils/IOUtils:close	(Ljava/io/Closeable;)V
    //   536: aload 6
    //   538: invokestatic 171	com/wandoujia/base/utils/IOUtils:close	(Ljava/io/Closeable;)V
    //   541: lload_2
    //   542: lconst_0
    //   543: lcmp
    //   544: ifle +19 -> 563
    //   547: iload 4
    //   549: ifeq +30 -> 579
    //   552: aload_0
    //   553: getfield 12	com/wandoujia/log/h:a	Lcom/wandoujia/log/LogSender;
    //   556: invokestatic 57	com/wandoujia/log/LogSender:access$800	(Lcom/wandoujia/log/LogSender;)Lcom/wandoujia/log/i;
    //   559: lload_2
    //   560: invokevirtual 174	com/wandoujia/log/i:a	(J)V
    //   563: aload 5
    //   565: ifnull -273 -> 292
    //   568: aload 5
    //   570: invokeinterface 179 1 0
    //   575: return
    //   576: astore 17
    //   578: return
    //   579: aload_0
    //   580: getfield 12	com/wandoujia/log/h:a	Lcom/wandoujia/log/LogSender;
    //   583: invokestatic 57	com/wandoujia/log/LogSender:access$800	(Lcom/wandoujia/log/LogSender;)Lcom/wandoujia/log/i;
    //   586: lload_2
    //   587: invokevirtual 182	com/wandoujia/log/i:b	(J)V
    //   590: goto -27 -> 563
    //   593: astore 47
    //   595: aload 47
    //   597: astore 20
    //   599: lload_2
    //   600: lstore 48
    //   602: iconst_0
    //   603: istore 24
    //   605: aconst_null
    //   606: astore 23
    //   608: lload 48
    //   610: lstore 25
    //   612: aload_1
    //   613: invokestatic 171	com/wandoujia/base/utils/IOUtils:close	(Ljava/io/Closeable;)V
    //   616: aload 23
    //   618: invokestatic 171	com/wandoujia/base/utils/IOUtils:close	(Ljava/io/Closeable;)V
    //   621: lload 25
    //   623: lconst_0
    //   624: lcmp
    //   625: ifle +20 -> 645
    //   628: iload 24
    //   630: ifeq +30 -> 660
    //   633: aload_0
    //   634: getfield 12	com/wandoujia/log/h:a	Lcom/wandoujia/log/LogSender;
    //   637: invokestatic 57	com/wandoujia/log/LogSender:access$800	(Lcom/wandoujia/log/LogSender;)Lcom/wandoujia/log/i;
    //   640: lload 25
    //   642: invokevirtual 174	com/wandoujia/log/i:a	(J)V
    //   645: aload 5
    //   647: ifnull +10 -> 657
    //   650: aload 5
    //   652: invokeinterface 179 1 0
    //   657: aload 20
    //   659: athrow
    //   660: aload_0
    //   661: getfield 12	com/wandoujia/log/h:a	Lcom/wandoujia/log/LogSender;
    //   664: invokestatic 57	com/wandoujia/log/LogSender:access$800	(Lcom/wandoujia/log/LogSender;)Lcom/wandoujia/log/i;
    //   667: lload 25
    //   669: invokevirtual 182	com/wandoujia/log/i:b	(J)V
    //   672: goto -27 -> 645
    //   675: astore 37
    //   677: return
    //   678: astore 27
    //   680: goto -23 -> 657
    //   683: astore 44
    //   685: aload 44
    //   687: astore 20
    //   689: lload_2
    //   690: lstore 45
    //   692: aload 6
    //   694: astore 23
    //   696: lload 45
    //   698: lstore 25
    //   700: aconst_null
    //   701: astore 5
    //   703: iconst_0
    //   704: istore 24
    //   706: aconst_null
    //   707: astore_1
    //   708: goto -96 -> 612
    //   711: astore 18
    //   713: aload 7
    //   715: astore_1
    //   716: iload 4
    //   718: istore 19
    //   720: aload 18
    //   722: astore 20
    //   724: lload_2
    //   725: lstore 21
    //   727: aload 6
    //   729: astore 23
    //   731: iload 19
    //   733: istore 24
    //   735: lload 21
    //   737: lstore 25
    //   739: goto -127 -> 612
    //   742: astore 43
    //   744: iconst_0
    //   745: istore 4
    //   747: aconst_null
    //   748: astore 5
    //   750: aconst_null
    //   751: astore 7
    //   753: goto -222 -> 531
    //   756: astore 16
    //   758: goto -227 -> 531
    //   761: astore 42
    //   763: iconst_0
    //   764: istore 4
    //   766: aconst_null
    //   767: astore 5
    //   769: aconst_null
    //   770: astore 7
    //   772: goto -311 -> 461
    //   775: astore 14
    //   777: goto -316 -> 461
    //   780: astore 41
    //   782: iconst_0
    //   783: istore 4
    //   785: aconst_null
    //   786: astore 5
    //   788: aconst_null
    //   789: astore 7
    //   791: goto -400 -> 391
    //   794: astore 12
    //   796: goto -405 -> 391
    //   799: astore 40
    //   801: aconst_null
    //   802: astore 9
    //   804: iconst_0
    //   805: istore 10
    //   807: aconst_null
    //   808: astore 7
    //   810: goto -489 -> 321
    //   813: astore 8
    //   815: aconst_null
    //   816: astore 9
    //   818: iconst_0
    //   819: istore 10
    //   821: goto -500 -> 321
    //   824: astore 34
    //   826: aload 5
    //   828: astore 35
    //   830: iload 4
    //   832: istore 10
    //   834: aload 35
    //   836: astore 9
    //   838: goto -517 -> 321
    //
    // Exception table:
    //   from	to	target	type
    //   12	21	307	java/lang/OutOfMemoryError
    //   358	365	366	java/io/IOException
    //   12	21	383	java/security/GeneralSecurityException
    //   428	435	436	java/io/IOException
    //   12	21	453	java/io/IOException
    //   498	505	506	java/io/IOException
    //   12	21	523	java/lang/Exception
    //   568	575	576	java/io/IOException
    //   12	21	593	finally
    //   285	292	675	java/io/IOException
    //   650	657	678	java/io/IOException
    //   21	35	683	finally
    //   35	127	711	finally
    //   138	153	711	finally
    //   153	178	711	finally
    //   182	196	711	finally
    //   210	248	711	finally
    //   21	35	742	java/lang/Exception
    //   35	127	756	java/lang/Exception
    //   138	153	756	java/lang/Exception
    //   153	178	756	java/lang/Exception
    //   182	196	756	java/lang/Exception
    //   210	248	756	java/lang/Exception
    //   21	35	761	java/io/IOException
    //   35	127	775	java/io/IOException
    //   138	153	775	java/io/IOException
    //   153	178	775	java/io/IOException
    //   182	196	775	java/io/IOException
    //   210	248	775	java/io/IOException
    //   21	35	780	java/security/GeneralSecurityException
    //   35	127	794	java/security/GeneralSecurityException
    //   138	153	794	java/security/GeneralSecurityException
    //   153	178	794	java/security/GeneralSecurityException
    //   182	196	794	java/security/GeneralSecurityException
    //   210	248	794	java/security/GeneralSecurityException
    //   21	35	799	java/lang/OutOfMemoryError
    //   35	127	813	java/lang/OutOfMemoryError
    //   138	153	813	java/lang/OutOfMemoryError
    //   153	178	813	java/lang/OutOfMemoryError
    //   182	196	824	java/lang/OutOfMemoryError
    //   210	248	824	java/lang/OutOfMemoryError
  }
}

/* Location:           C:\WorkSpace\WandDouJiaNotificationBar\WanDou1.jar
 * Qualified Name:     com.wandoujia.log.h
 * JD-Core Version:    0.6.0
 */