package com.tencent.open.yyb;

import android.content.Context;
import android.content.Intent;
import android.graphics.Rect;
import android.graphics.drawable.Drawable;
import android.os.Bundle;
import android.view.View;
import com.tencent.open.a.f;
import com.tencent.tauth.d;
import com.unionpay.uppay.c;
import java.io.UnsupportedEncodingException;
import java.net.URLDecoder;

public final class a
  implements com.tencent.tauth.b
{
  public View a;

  public static Drawable a(String paramString, Context paramContext)
  {
    return a(paramString, paramContext, new Rect(0, 0, 0, 0));
  }

  // ERROR //
  public static Drawable a(String paramString, Context paramContext, Rect paramRect)
  {
    // Byte code:
    //   0: aload_1
    //   1: invokevirtual 31	android/content/Context:getApplicationContext	()Landroid/content/Context;
    //   4: astore_3
    //   5: aload_3
    //   6: invokevirtual 35	android/content/Context:getAssets	()Landroid/content/res/AssetManager;
    //   9: astore 4
    //   11: aload 4
    //   13: aload_0
    //   14: invokevirtual 41	android/content/res/AssetManager:open	(Ljava/lang/String;)Ljava/io/InputStream;
    //   17: astore 14
    //   19: aload 14
    //   21: astore 6
    //   23: aload 6
    //   25: ifnonnull +28 -> 53
    //   28: aload 6
    //   30: ifnull +8 -> 38
    //   33: aload 6
    //   35: invokevirtual 46	java/io/InputStream:close	()V
    //   38: aconst_null
    //   39: areturn
    //   40: astore 20
    //   42: ldc 48
    //   44: ldc 50
    //   46: aload 20
    //   48: invokestatic 56	com/tencent/open/a/f:b	(Ljava/lang/String;Ljava/lang/String;Ljava/lang/Throwable;)V
    //   51: aconst_null
    //   52: areturn
    //   53: aload_0
    //   54: ldc 58
    //   56: invokevirtual 64	java/lang/String:endsWith	(Ljava/lang/String;)Z
    //   59: ifeq +79 -> 138
    //   62: aload 6
    //   64: invokestatic 70	android/graphics/BitmapFactory:decodeStream	(Ljava/io/InputStream;)Landroid/graphics/Bitmap;
    //   67: astore 17
    //   69: aload 17
    //   71: ifnull +42 -> 113
    //   74: aload 17
    //   76: invokevirtual 76	android/graphics/Bitmap:getNinePatchChunk	()[B
    //   79: astore 18
    //   81: new 78	android/graphics/drawable/NinePatchDrawable
    //   84: dup
    //   85: aload_3
    //   86: invokevirtual 82	android/content/Context:getResources	()Landroid/content/res/Resources;
    //   89: aload 17
    //   91: aload 18
    //   93: aload_2
    //   94: aconst_null
    //   95: invokespecial 85	android/graphics/drawable/NinePatchDrawable:<init>	(Landroid/content/res/Resources;Landroid/graphics/Bitmap;[BLandroid/graphics/Rect;Ljava/lang/String;)V
    //   98: astore 9
    //   100: aload 6
    //   102: ifnull +8 -> 110
    //   105: aload 6
    //   107: invokevirtual 46	java/io/InputStream:close	()V
    //   110: aload 9
    //   112: areturn
    //   113: aload 6
    //   115: ifnull -77 -> 38
    //   118: aload 6
    //   120: invokevirtual 46	java/io/InputStream:close	()V
    //   123: aconst_null
    //   124: areturn
    //   125: astore 19
    //   127: ldc 48
    //   129: ldc 50
    //   131: aload 19
    //   133: invokestatic 56	com/tencent/open/a/f:b	(Ljava/lang/String;Ljava/lang/String;Ljava/lang/Throwable;)V
    //   136: aconst_null
    //   137: areturn
    //   138: aload 6
    //   140: aload_0
    //   141: invokestatic 91	android/graphics/drawable/Drawable:createFromStream	(Ljava/io/InputStream;Ljava/lang/String;)Landroid/graphics/drawable/Drawable;
    //   144: astore 15
    //   146: aload 15
    //   148: astore 9
    //   150: goto -50 -> 100
    //   153: astore 16
    //   155: ldc 48
    //   157: ldc 50
    //   159: aload 16
    //   161: invokestatic 56	com/tencent/open/a/f:b	(Ljava/lang/String;Ljava/lang/String;Ljava/lang/Throwable;)V
    //   164: goto -54 -> 110
    //   167: astore 11
    //   169: aconst_null
    //   170: astore 12
    //   172: ldc 48
    //   174: ldc 93
    //   176: aload 11
    //   178: invokestatic 56	com/tencent/open/a/f:b	(Ljava/lang/String;Ljava/lang/String;Ljava/lang/Throwable;)V
    //   181: aload 12
    //   183: ifnull +138 -> 321
    //   186: aload 12
    //   188: invokevirtual 46	java/io/InputStream:close	()V
    //   191: aconst_null
    //   192: astore 9
    //   194: goto -84 -> 110
    //   197: astore 13
    //   199: ldc 48
    //   201: ldc 50
    //   203: aload 13
    //   205: invokestatic 56	com/tencent/open/a/f:b	(Ljava/lang/String;Ljava/lang/String;Ljava/lang/Throwable;)V
    //   208: aconst_null
    //   209: astore 9
    //   211: goto -101 -> 110
    //   214: astore 8
    //   216: aconst_null
    //   217: astore 6
    //   219: ldc 48
    //   221: ldc 50
    //   223: aload 8
    //   225: invokestatic 56	com/tencent/open/a/f:b	(Ljava/lang/String;Ljava/lang/String;Ljava/lang/Throwable;)V
    //   228: aload 6
    //   230: ifnull +91 -> 321
    //   233: aload 6
    //   235: invokevirtual 46	java/io/InputStream:close	()V
    //   238: aconst_null
    //   239: astore 9
    //   241: goto -131 -> 110
    //   244: astore 10
    //   246: ldc 48
    //   248: ldc 50
    //   250: aload 10
    //   252: invokestatic 56	com/tencent/open/a/f:b	(Ljava/lang/String;Ljava/lang/String;Ljava/lang/Throwable;)V
    //   255: aconst_null
    //   256: astore 9
    //   258: goto -148 -> 110
    //   261: astore 5
    //   263: aconst_null
    //   264: astore 6
    //   266: aload 6
    //   268: ifnull +8 -> 276
    //   271: aload 6
    //   273: invokevirtual 46	java/io/InputStream:close	()V
    //   276: aload 5
    //   278: athrow
    //   279: astore 7
    //   281: ldc 48
    //   283: ldc 50
    //   285: aload 7
    //   287: invokestatic 56	com/tencent/open/a/f:b	(Ljava/lang/String;Ljava/lang/String;Ljava/lang/Throwable;)V
    //   290: goto -14 -> 276
    //   293: astore 5
    //   295: goto -29 -> 266
    //   298: astore 5
    //   300: aload 12
    //   302: astore 6
    //   304: goto -38 -> 266
    //   307: astore 8
    //   309: goto -90 -> 219
    //   312: astore 11
    //   314: aload 6
    //   316: astore 12
    //   318: goto -146 -> 172
    //   321: aconst_null
    //   322: astore 9
    //   324: goto -214 -> 110
    //
    // Exception table:
    //   from	to	target	type
    //   33	38	40	java/io/IOException
    //   118	123	125	java/io/IOException
    //   105	110	153	java/io/IOException
    //   11	19	167	java/lang/OutOfMemoryError
    //   186	191	197	java/io/IOException
    //   11	19	214	java/io/IOException
    //   233	238	244	java/io/IOException
    //   11	19	261	finally
    //   271	276	279	java/io/IOException
    //   53	69	293	finally
    //   74	100	293	finally
    //   138	146	293	finally
    //   219	228	293	finally
    //   172	181	298	finally
    //   53	69	307	java/io/IOException
    //   74	100	307	java/io/IOException
    //   138	146	307	java/io/IOException
    //   53	69	312	java/lang/OutOfMemoryError
    //   74	100	312	java/lang/OutOfMemoryError
    //   138	146	312	java/lang/OutOfMemoryError
  }

  // ERROR //
  private static String a(String paramString)
  {
    // Byte code:
    //   0: aload_0
    //   1: ifnull +71 -> 72
    //   4: aload_0
    //   5: invokestatic 101	java/net/URLDecoder:decode	(Ljava/lang/String;)Ljava/lang/String;
    //   8: astore_1
    //   9: aload_1
    //   10: ifnull +50 -> 60
    //   13: aload_1
    //   14: invokestatic 106	com/unionpay/mpay/utils/b:a	(Ljava/lang/String;)[B
    //   17: astore 7
    //   19: aload 7
    //   21: astore_2
    //   22: aload_2
    //   23: ifnull +44 -> 67
    //   26: new 60	java/lang/String
    //   29: dup
    //   30: aload_2
    //   31: ldc 108
    //   33: invokespecial 111	java/lang/String:<init>	([BLjava/lang/String;)V
    //   36: astore_3
    //   37: new 113	java/lang/StringBuilder
    //   40: dup
    //   41: ldc 115
    //   43: invokespecial 118	java/lang/StringBuilder:<init>	(Ljava/lang/String;)V
    //   46: aload_3
    //   47: invokevirtual 122	java/lang/StringBuilder:append	(Ljava/lang/String;)Ljava/lang/StringBuilder;
    //   50: ldc 124
    //   52: invokevirtual 122	java/lang/StringBuilder:append	(Ljava/lang/String;)Ljava/lang/StringBuilder;
    //   55: pop
    //   56: aload_3
    //   57: areturn
    //   58: astore 6
    //   60: aconst_null
    //   61: astore_2
    //   62: goto -40 -> 22
    //   65: astore 5
    //   67: aconst_null
    //   68: astore_3
    //   69: goto -32 -> 37
    //   72: aconst_null
    //   73: astore_1
    //   74: goto -65 -> 9
    //
    // Exception table:
    //   from	to	target	type
    //   13	19	58	java/io/IOException
    //   26	37	65	java/io/UnsupportedEncodingException
  }

  public static void a(String paramString1, String paramString2, String paramString3)
  {
    Bundle localBundle = new Bundle();
    localBundle.putString("uin", "1000");
    localBundle.putString("action", paramString2);
    localBundle.putString("appid", paramString1);
    localBundle.putString("via", paramString3);
    new k(0).execute(new Bundle[] { localBundle });
  }

  public static boolean a(Intent paramIntent, com.unionpay.uppay.b paramb)
  {
    boolean bool1 = false;
    if (paramIntent == null);
    label568: 
    while (true)
    {
      return bool1;
      String str1 = paramIntent.getDataString();
      Bundle localBundle = paramIntent.getExtras();
      if ((str1 != null) && (str1.length() > 0))
      {
        paramb.x.a = 1000;
        int i = paramb.x.a;
        bool1 = false;
        switch (i)
        {
        default:
        case 0:
        case 2:
        case 1:
        case 3:
        case 4:
        case 1000:
        }
      }
      while (true)
      {
        if ((paramb.x.a != 2) && (paramb.x.a != 3))
          break label568;
        paramb.x.d = true;
        return bool1;
        if (localBundle == null)
          break;
        paramb.x.a = localBundle.getInt("reqOriginalId");
        new StringBuilder("reqID:").append(paramb.x.a);
        localBundle.getBoolean("invokedbyplugin");
        break;
        paramb.x.c = localBundle.getString("ex_mode");
        new StringBuilder("mServerIdentifier = ").append(paramb.x.c);
        paramb.a = localBundle.getString("tn");
        paramb.b = localBundle.getString("appID");
        if (paramb.b == null)
          paramb.b = "";
        String str5 = localBundle.getString("frontNotifyByPlugin");
        if ((str5 == null) || (str5.length() == 0));
        for (boolean bool2 = true; ; bool2 = false)
        {
          paramb.H = bool2;
          String str6 = paramb.a;
          bool1 = false;
          if (str6 != null)
          {
            int m = paramb.a.trim().length();
            bool1 = false;
            if (m > 0)
            {
              new StringBuilder("tn from bundle:").append(paramb.a);
              bool1 = true;
            }
          }
          paramb.i = localBundle.getString("ResultURL");
          new StringBuilder("result URL:").append(paramb.i);
          break;
        }
        String str4 = localBundle.getString("uppayuri");
        paramb.x.b = localBundle.getString("resultIntentAction");
        bool1 = a(str4, paramb);
        continue;
        paramb.x.c = localBundle.getString("ex_mode");
        paramb.x.f = localBundle.getString("tencentUID");
        paramb.x.g = localBundle.getString("tencentWID");
        paramb.a = localBundle.getString("tn");
        String str2 = paramb.a;
        bool1 = false;
        if (str2 == null)
          continue;
        int j = paramb.a.trim().length();
        bool1 = false;
        if (j <= 0)
          continue;
        String str3 = paramb.x.g;
        bool1 = false;
        if (str3 == null)
          continue;
        int k = paramb.x.g.trim().length();
        bool1 = false;
        if (k <= 0)
          continue;
        bool1 = true;
        continue;
        bool1 = b(a(localBundle.getString("paydata")), paramb);
        continue;
        bool1 = a(str1, paramb);
      }
    }
  }

  private static boolean a(String paramString, com.unionpay.uppay.b paramb)
  {
    String str = null;
    if (paramString != null)
    {
      String[] arrayOfString1 = paramString.split("\\?");
      if (arrayOfString1.length >= 2)
      {
        String[] arrayOfString2 = arrayOfString1[1].split("&");
        int i = arrayOfString2.length;
        int j = 0;
        Object localObject = null;
        if (j < i)
        {
          String[] arrayOfString3 = arrayOfString2[j].split("=");
          if (arrayOfString3.length >= 2)
          {
            if (!arrayOfString3[0].equalsIgnoreCase("style"))
              break label94;
            localObject = arrayOfString3[1];
          }
          while (true)
          {
            j++;
            break;
            label94: if (!arrayOfString3[0].equalsIgnoreCase("paydata"))
              continue;
            str = arrayOfString3[1];
          }
        }
        if ((localObject != null) && (localObject.equalsIgnoreCase("token")) && (str != null))
          return b(a(str), paramb);
      }
    }
    return false;
  }

  private static String b(String paramString1, String paramString2, String paramString3)
  {
    String str1 = paramString1 + "=" + paramString2;
    if (paramString3 != null)
    {
      String str2 = str1 + "; path=/";
      str1 = str2 + "; domain=" + paramString3;
    }
    return str1;
  }

  private static boolean b(String paramString, com.unionpay.uppay.b paramb)
  {
    int i = 1;
    if ((paramString == null) || (paramString.length() == 0))
      i = 0;
    label103: 
    do
    {
      return i;
      paramb.x.c = "00";
      String[] arrayOfString1 = paramString.split(",");
      int j = arrayOfString1.length;
      int k = 0;
      if (k >= j)
        continue;
      String[] arrayOfString2 = arrayOfString1[k].trim().split("=");
      if (arrayOfString2.length >= 2)
      {
        if (!arrayOfString2[0].trim().equalsIgnoreCase("tn"))
          break label103;
        paramb.a = arrayOfString2[i].trim();
      }
      while (true)
      {
        k++;
        break;
        if (arrayOfString2[0].trim().equalsIgnoreCase("usetestmode"))
        {
          if (arrayOfString2[i].trim().equalsIgnoreCase("true"))
          {
            paramb.x.c = "01";
            continue;
          }
          if (arrayOfString2[i].trim().equalsIgnoreCase("test"))
          {
            paramb.x.c = "02";
            continue;
          }
          if (!arrayOfString2[i].trim().equalsIgnoreCase("inner"))
            continue;
          paramb.x.c = "98";
          continue;
        }
        if (!arrayOfString2[0].trim().equalsIgnoreCase("ResultURL"))
          continue;
        try
        {
          paramb.i = URLDecoder.decode(arrayOfString2[1].trim(), "UTF-8");
        }
        catch (UnsupportedEncodingException localUnsupportedEncodingException)
        {
        }
      }
    }
    while ((paramb.a != null) && (paramb.a.length() > 0) && (paramb.i != null) && (paramb.i.length() > 0));
    return false;
  }

  public final void a(d paramd)
  {
    f.b("openSDK_LOG.AppbarActivity", "-->(AppbarJsBridge)openLoginActivity onError" + paramd.b);
    AppbarActivity.b(null).a("loginCallback", 0, null, -5);
  }

  // ERROR //
  public final void a(Object paramObject)
  {
    // Byte code:
    //   0: ldc_w 309
    //   3: ldc_w 333
    //   6: invokestatic 316	com/tencent/open/a/f:b	(Ljava/lang/String;Ljava/lang/String;)V
    //   9: aload_1
    //   10: checkcast 335	org/json/JSONObject
    //   13: astore_2
    //   14: aload_2
    //   15: ldc_w 337
    //   18: iconst_m1
    //   19: invokevirtual 341	org/json/JSONObject:optInt	(Ljava/lang/String;I)I
    //   22: ifeq +18 -> 40
    //   25: aconst_null
    //   26: invokestatic 321	com/tencent/open/yyb/AppbarActivity:b	(Lcom/tencent/open/yyb/AppbarActivity;)Lcom/tencent/open/yyb/h;
    //   29: ldc_w 323
    //   32: iconst_0
    //   33: aconst_null
    //   34: bipush 251
    //   36: invokevirtual 328	com/tencent/open/yyb/h:a	(Ljava/lang/String;ILjava/lang/String;I)V
    //   39: return
    //   40: aload_2
    //   41: ldc_w 343
    //   44: invokevirtual 344	org/json/JSONObject:getString	(Ljava/lang/String;)Ljava/lang/String;
    //   47: astore 4
    //   49: aload_2
    //   50: ldc_w 346
    //   53: invokevirtual 344	org/json/JSONObject:getString	(Ljava/lang/String;)Ljava/lang/String;
    //   56: astore 5
    //   58: aload_2
    //   59: ldc_w 348
    //   62: invokevirtual 344	org/json/JSONObject:getString	(Ljava/lang/String;)Ljava/lang/String;
    //   65: pop
    //   66: aconst_null
    //   67: invokestatic 351	com/tencent/open/yyb/AppbarActivity:c	(Lcom/tencent/open/yyb/AppbarActivity;)Lcom/tencent/connect/b/c;
    //   70: invokevirtual 355	com/tencent/connect/b/c:b	()Ljava/lang/String;
    //   73: astore 7
    //   75: invokestatic 358	com/tencent/open/yyb/AppbarActivity:a	()Lcom/tencent/open/c/b;
    //   78: invokevirtual 363	com/tencent/open/c/b:getUrl	()Ljava/lang/String;
    //   81: astore 8
    //   83: aload 8
    //   85: invokestatic 369	android/text/TextUtils:isEmpty	(Ljava/lang/CharSequence;)Z
    //   88: ifne +119 -> 207
    //   91: aconst_null
    //   92: invokestatic 375	android/webkit/CookieSyncManager:createInstance	(Landroid/content/Context;)Landroid/webkit/CookieSyncManager;
    //   95: pop
    //   96: invokestatic 381	android/webkit/CookieManager:getInstance	()Landroid/webkit/CookieManager;
    //   99: astore 17
    //   101: aload 17
    //   103: iconst_1
    //   104: invokevirtual 385	android/webkit/CookieManager:setAcceptCookie	(Z)V
    //   107: aload 8
    //   109: invokestatic 391	android/net/Uri:parse	(Ljava/lang/String;)Landroid/net/Uri;
    //   112: invokevirtual 394	android/net/Uri:getHost	()Ljava/lang/String;
    //   115: invokevirtual 397	java/lang/String:toLowerCase	()Ljava/lang/String;
    //   118: ldc_w 399
    //   121: invokevirtual 64	java/lang/String:endsWith	(Ljava/lang/String;)Z
    //   124: ifeq +223 -> 347
    //   127: ldc_w 399
    //   130: astore 18
    //   132: aload 17
    //   134: aload 8
    //   136: ldc_w 401
    //   139: ldc_w 403
    //   142: aload 18
    //   144: invokestatic 405	com/tencent/open/yyb/a:b	(Ljava/lang/String;Ljava/lang/String;Ljava/lang/String;)Ljava/lang/String;
    //   147: invokevirtual 408	android/webkit/CookieManager:setCookie	(Ljava/lang/String;Ljava/lang/String;)V
    //   150: aload 17
    //   152: aload 8
    //   154: ldc_w 410
    //   157: aload 4
    //   159: aload 18
    //   161: invokestatic 405	com/tencent/open/yyb/a:b	(Ljava/lang/String;Ljava/lang/String;Ljava/lang/String;)Ljava/lang/String;
    //   164: invokevirtual 408	android/webkit/CookieManager:setCookie	(Ljava/lang/String;Ljava/lang/String;)V
    //   167: aload 17
    //   169: aload 8
    //   171: ldc_w 412
    //   174: aload 5
    //   176: aload 18
    //   178: invokestatic 405	com/tencent/open/yyb/a:b	(Ljava/lang/String;Ljava/lang/String;Ljava/lang/String;)Ljava/lang/String;
    //   181: invokevirtual 408	android/webkit/CookieManager:setCookie	(Ljava/lang/String;Ljava/lang/String;)V
    //   184: aload 17
    //   186: aload 8
    //   188: ldc_w 414
    //   191: aload 7
    //   193: aload 18
    //   195: invokestatic 405	com/tencent/open/yyb/a:b	(Ljava/lang/String;Ljava/lang/String;Ljava/lang/String;)Ljava/lang/String;
    //   198: invokevirtual 408	android/webkit/CookieManager:setCookie	(Ljava/lang/String;Ljava/lang/String;)V
    //   201: invokestatic 417	android/webkit/CookieSyncManager:getInstance	()Landroid/webkit/CookieSyncManager;
    //   204: invokevirtual 420	android/webkit/CookieSyncManager:sync	()V
    //   207: new 335	org/json/JSONObject
    //   210: dup
    //   211: invokespecial 421	org/json/JSONObject:<init>	()V
    //   214: astore 9
    //   216: aload 9
    //   218: ldc_w 401
    //   221: ldc_w 423
    //   224: invokevirtual 427	org/json/JSONObject:put	(Ljava/lang/String;Ljava/lang/Object;)Lorg/json/JSONObject;
    //   227: pop
    //   228: aload 9
    //   230: ldc_w 343
    //   233: aload 4
    //   235: invokevirtual 427	org/json/JSONObject:put	(Ljava/lang/String;Ljava/lang/Object;)Lorg/json/JSONObject;
    //   238: pop
    //   239: aload 9
    //   241: ldc_w 429
    //   244: aload 5
    //   246: invokevirtual 427	org/json/JSONObject:put	(Ljava/lang/String;Ljava/lang/Object;)Lorg/json/JSONObject;
    //   249: pop
    //   250: aconst_null
    //   251: invokestatic 321	com/tencent/open/yyb/AppbarActivity:b	(Lcom/tencent/open/yyb/AppbarActivity;)Lcom/tencent/open/yyb/h;
    //   254: ldc_w 323
    //   257: iconst_0
    //   258: aload 9
    //   260: invokevirtual 430	org/json/JSONObject:toString	()Ljava/lang/String;
    //   263: invokevirtual 433	com/tencent/open/yyb/h:a	(Ljava/lang/String;ILjava/lang/String;)V
    //   266: new 154	android/content/Intent
    //   269: dup
    //   270: invokespecial 434	android/content/Intent:<init>	()V
    //   273: astore 14
    //   275: aload 14
    //   277: ldc_w 436
    //   280: aload_2
    //   281: invokevirtual 430	org/json/JSONObject:toString	()Ljava/lang/String;
    //   284: invokevirtual 440	android/content/Intent:putExtra	(Ljava/lang/String;Ljava/lang/String;)Landroid/content/Intent;
    //   287: pop
    //   288: aconst_null
    //   289: iconst_m1
    //   290: aload 14
    //   292: invokevirtual 444	com/tencent/open/yyb/AppbarActivity:setResult	(ILandroid/content/Intent;)V
    //   295: return
    //   296: astore_3
    //   297: aconst_null
    //   298: invokestatic 321	com/tencent/open/yyb/AppbarActivity:b	(Lcom/tencent/open/yyb/AppbarActivity;)Lcom/tencent/open/yyb/h;
    //   301: ldc_w 323
    //   304: iconst_0
    //   305: aconst_null
    //   306: bipush 251
    //   308: invokevirtual 328	com/tencent/open/yyb/h:a	(Ljava/lang/String;ILjava/lang/String;I)V
    //   311: ldc_w 309
    //   314: ldc_w 446
    //   317: invokestatic 316	com/tencent/open/a/f:b	(Ljava/lang/String;Ljava/lang/String;)V
    //   320: return
    //   321: astore 10
    //   323: aconst_null
    //   324: invokestatic 321	com/tencent/open/yyb/AppbarActivity:b	(Lcom/tencent/open/yyb/AppbarActivity;)Lcom/tencent/open/yyb/h;
    //   327: ldc_w 323
    //   330: iconst_0
    //   331: aconst_null
    //   332: bipush 251
    //   334: invokevirtual 328	com/tencent/open/yyb/h:a	(Ljava/lang/String;ILjava/lang/String;I)V
    //   337: ldc_w 309
    //   340: ldc_w 448
    //   343: invokestatic 316	com/tencent/open/a/f:b	(Ljava/lang/String;Ljava/lang/String;)V
    //   346: return
    //   347: aconst_null
    //   348: astore 18
    //   350: goto -218 -> 132
    //
    // Exception table:
    //   from	to	target	type
    //   40	75	296	org/json/JSONException
    //   216	250	321	org/json/JSONException
  }
}

/* Location:           C:\WorkSpace\WandDouJiaNotificationBar\WanDou1.jar
 * Qualified Name:     com.tencent.open.yyb.a
 * JD-Core Version:    0.6.0
 */