import java.util.concurrent.Callable;

final class atn
  implements Callable
{
  atn(atj paramatj)
  {
  }

  // ERROR //
  private atq a()
  {
    // Byte code:
    //   0: aload_0
    //   1: getfield 12	atn:a	Latj;
    //   4: getfield 30	atj:p	Lasz;
    //   7: ifnull +47 -> 54
    //   10: aload_0
    //   11: getfield 12	atn:a	Latj;
    //   14: getfield 30	atj:p	Lasz;
    //   17: astore 11
    //   19: aload 11
    //   21: iconst_1
    //   22: putfield 36	asz:e	Z
    //   25: aload 11
    //   27: getfield 40	asz:d	Landroid/os/Handler;
    //   30: new 42	atb
    //   33: dup
    //   34: aload 11
    //   36: invokespecial 45	atb:<init>	(Lasz;)V
    //   39: invokevirtual 51	android/os/Handler:post	(Ljava/lang/Runnable;)Z
    //   42: pop
    //   43: aload 11
    //   45: getfield 55	asz:c	Latd;
    //   48: getfield 60	atd:a	Lcom/google/android/libraries/appstreaming/framework/NativeControlStreamer;
    //   51: invokevirtual 65	com/google/android/libraries/appstreaming/framework/NativeControlStreamer:release	()V
    //   54: aload_0
    //   55: getfield 12	atn:a	Latj;
    //   58: getfield 69	atj:q	Laub;
    //   61: ifnull +45 -> 106
    //   64: aload_0
    //   65: getfield 12	atn:a	Latj;
    //   68: getfield 69	atj:q	Laub;
    //   71: astore 6
    //   73: aload 6
    //   75: getfield 74	aub:d	Lcom/google/android/libraries/appstreaming/framework/NativeVideoPlayer;
    //   78: invokevirtual 79	com/google/android/libraries/appstreaming/framework/NativeVideoPlayer:stop	()V
    //   81: aload 6
    //   83: getfield 82	aub:e	Ljava/util/concurrent/Future;
    //   86: ifnull +20 -> 106
    //   89: aload 6
    //   91: getfield 82	aub:e	Ljava/util/concurrent/Future;
    //   94: ldc2_w 83
    //   97: getstatic 90	java/util/concurrent/TimeUnit:MILLISECONDS	Ljava/util/concurrent/TimeUnit;
    //   100: invokeinterface 96 4 0
    //   105: pop
    //   106: aload_0
    //   107: getfield 12	atn:a	Latj;
    //   110: getfield 100	atj:r	Lasu;
    //   113: ifnull +13 -> 126
    //   116: aload_0
    //   117: getfield 12	atn:a	Latj;
    //   120: getfield 100	atj:r	Lasu;
    //   123: invokevirtual 105	asu:b	()V
    //   126: aload_0
    //   127: getfield 12	atn:a	Latj;
    //   130: getfield 109	atj:f	Lasj;
    //   133: ifnull +83 -> 216
    //   136: aload_0
    //   137: getfield 12	atn:a	Latj;
    //   140: getfield 109	atj:f	Lasj;
    //   143: ldc2_w 83
    //   146: invokevirtual 114	asj:a	(J)Z
    //   149: pop
    //   150: aload_0
    //   151: getfield 12	atn:a	Latj;
    //   154: getfield 109	atj:f	Lasj;
    //   157: astore_3
    //   158: aload_3
    //   159: getfield 118	asj:h	Ljava/util/concurrent/atomic/AtomicBoolean;
    //   162: iconst_1
    //   163: invokevirtual 124	java/util/concurrent/atomic/AtomicBoolean:set	(Z)V
    //   166: aload_3
    //   167: getfield 128	asj:i	Ljava/net/Socket;
    //   170: ifnull +10 -> 180
    //   173: aload_3
    //   174: getfield 128	asj:i	Ljava/net/Socket;
    //   177: invokevirtual 133	java/net/Socket:close	()V
    //   180: aload_3
    //   181: getfield 135	asj:b	Ljava/util/concurrent/Future;
    //   184: ifnull +14 -> 198
    //   187: aload_3
    //   188: getfield 135	asj:b	Ljava/util/concurrent/Future;
    //   191: iconst_1
    //   192: invokeinterface 139 2 0
    //   197: pop
    //   198: aload_3
    //   199: getfield 141	asj:c	Ljava/util/concurrent/Future;
    //   202: ifnull +14 -> 216
    //   205: aload_3
    //   206: getfield 141	asj:c	Ljava/util/concurrent/Future;
    //   209: iconst_1
    //   210: invokeinterface 139 2 0
    //   215: pop
    //   216: new 143	atq
    //   219: dup
    //   220: invokespecial 144	atq:<init>	()V
    //   223: areturn
    //   224: astore 7
    //   226: getstatic 147	aub:a	Ljava/util/logging/Logger;
    //   229: getstatic 152	asn:a	Ljava/util/logging/Level;
    //   232: ldc 154
    //   234: aload 7
    //   236: invokevirtual 160	java/util/logging/Logger:log	(Ljava/util/logging/Level;Ljava/lang/String;Ljava/lang/Throwable;)V
    //   239: aload 6
    //   241: getfield 82	aub:e	Ljava/util/concurrent/Future;
    //   244: iconst_1
    //   245: invokeinterface 139 2 0
    //   250: pop
    //   251: goto -145 -> 106
    //   254: astore 9
    //   256: getstatic 147	aub:a	Ljava/util/logging/Logger;
    //   259: getstatic 152	asn:a	Ljava/util/logging/Level;
    //   262: ldc 162
    //   264: aload 9
    //   266: invokevirtual 160	java/util/logging/Logger:log	(Ljava/util/logging/Level;Ljava/lang/String;Ljava/lang/Throwable;)V
    //   269: goto -163 -> 106
    //   272: astore_2
    //   273: getstatic 163	atj:a	Ljava/util/logging/Logger;
    //   276: getstatic 152	asn:a	Ljava/util/logging/Level;
    //   279: ldc 165
    //   281: aload_2
    //   282: invokevirtual 160	java/util/logging/Logger:log	(Ljava/util/logging/Level;Ljava/lang/String;Ljava/lang/Throwable;)V
    //   285: goto -69 -> 216
    //   288: astore 7
    //   290: goto -64 -> 226
    //
    // Exception table:
    //   from	to	target	type
    //   89	106	224	java/lang/InterruptedException
    //   89	106	254	java/util/concurrent/ExecutionException
    //   150	180	272	java/io/IOException
    //   180	198	272	java/io/IOException
    //   198	216	272	java/io/IOException
    //   89	106	288	java/util/concurrent/TimeoutException
  }
}

/* Location:           C:\Program Files\APK反编译\classes_dex2jar.jar
 * Qualified Name:     atn
 * JD-Core Version:    0.6.0
 */