import java.util.concurrent.Callable;

final class att
  implements Callable
{
  private final atp b;
  private final atv c;
  private final atw d;
  private final atr e;
  private final ats f;

  att(atj paramatj, atp paramatp, atv paramatv, atw paramatw, atr paramatr, ats paramats)
  {
    this.b = paramatp;
    this.c = paramatv;
    this.d = paramatw;
    this.e = paramatr;
    this.f = paramats;
  }

  // ERROR //
  private atq a()
  {
    // Byte code:
    //   0: aload_0
    //   1: getfield 22	att:a	Latj;
    //   4: getfield 47	atj:d	Lauz;
    //   7: ifnull +279 -> 286
    //   10: iconst_1
    //   11: istore_1
    //   12: invokestatic 49	atj:d	()V
    //   15: iload_1
    //   16: ifeq +275 -> 291
    //   19: aload_0
    //   20: getfield 22	att:a	Latj;
    //   23: getfield 47	atj:d	Lauz;
    //   26: getfield 54	auz:e	Lavk;
    //   29: iconst_0
    //   30: putfield 59	avk:d	I
    //   33: new 61	java/util/ArrayList
    //   36: dup
    //   37: iconst_3
    //   38: invokespecial 64	java/util/ArrayList:<init>	(I)V
    //   41: astore 11
    //   43: iconst_3
    //   44: anewarray 66	java/util/concurrent/Future
    //   47: astore 12
    //   49: aload 12
    //   51: iconst_0
    //   52: aload_0
    //   53: getfield 22	att:a	Latj;
    //   56: getfield 70	atj:l	Ljava/util/concurrent/CompletionService;
    //   59: aload_0
    //   60: getfield 35	att:f	Lats;
    //   63: invokeinterface 76 2 0
    //   68: aastore
    //   69: aload 12
    //   71: iconst_1
    //   72: aload_0
    //   73: getfield 22	att:a	Latj;
    //   76: getfield 70	atj:l	Ljava/util/concurrent/CompletionService;
    //   79: aload_0
    //   80: getfield 31	att:d	Latw;
    //   83: invokeinterface 76 2 0
    //   88: aastore
    //   89: aload 12
    //   91: iconst_2
    //   92: aload_0
    //   93: getfield 22	att:a	Latj;
    //   96: getfield 70	atj:l	Ljava/util/concurrent/CompletionService;
    //   99: aload_0
    //   100: getfield 29	att:c	Latv;
    //   103: invokeinterface 76 2 0
    //   108: aastore
    //   109: aload 11
    //   111: aload 12
    //   113: invokestatic 82	java/util/Collections:addAll	(Ljava/util/Collection;[Ljava/lang/Object;)Z
    //   116: pop
    //   117: new 84	atq
    //   120: dup
    //   121: invokespecial 85	atq:<init>	()V
    //   124: astore 14
    //   126: invokestatic 91	android/os/SystemClock:uptimeMillis	()J
    //   129: lstore 15
    //   131: lconst_0
    //   132: lstore 17
    //   134: aload 14
    //   136: astore 19
    //   138: iconst_0
    //   139: istore 20
    //   141: aload 11
    //   143: invokeinterface 97 1 0
    //   148: istore 27
    //   150: iload 20
    //   152: iload 27
    //   154: if_icmpge +493 -> 647
    //   157: getstatic 99	atj:b	I
    //   160: i2l
    //   161: lload 17
    //   163: lsub
    //   164: lconst_0
    //   165: invokestatic 105	java/lang/Math:max	(JJ)J
    //   168: lstore 41
    //   170: aload 11
    //   172: iload 20
    //   174: invokeinterface 109 2 0
    //   179: checkcast 66	java/util/concurrent/Future
    //   182: lload 41
    //   184: getstatic 115	java/util/concurrent/TimeUnit:MILLISECONDS	Ljava/util/concurrent/TimeUnit;
    //   187: invokeinterface 118 4 0
    //   192: checkcast 84	atq
    //   195: astore 39
    //   197: aload 39
    //   199: invokevirtual 121	atq:a	()Z
    //   202: istore 43
    //   204: iload 43
    //   206: ifne +628 -> 834
    //   209: invokestatic 91	android/os/SystemClock:uptimeMillis	()J
    //   212: lload 15
    //   214: lsub
    //   215: lstore 33
    //   217: getstatic 124	atj:a	Ljava/util/logging/Logger;
    //   220: astore 44
    //   222: getstatic 129	asn:d	Ljava/util/logging/Level;
    //   225: astore 45
    //   227: getstatic 135	java/util/Locale:US	Ljava/util/Locale;
    //   230: astore 46
    //   232: iconst_2
    //   233: anewarray 4	java/lang/Object
    //   236: astore 47
    //   238: aload 47
    //   240: iconst_0
    //   241: iload 20
    //   243: invokestatic 141	java/lang/Integer:valueOf	(I)Ljava/lang/Integer;
    //   246: aastore
    //   247: aload 47
    //   249: iconst_1
    //   250: lload 33
    //   252: invokestatic 146	java/lang/Long:valueOf	(J)Ljava/lang/Long;
    //   255: aastore
    //   256: aload 44
    //   258: aload 45
    //   260: aload 46
    //   262: ldc 148
    //   264: aload 47
    //   266: invokestatic 154	java/lang/String:format	(Ljava/util/Locale;Ljava/lang/String;[Ljava/lang/Object;)Ljava/lang/String;
    //   269: invokevirtual 160	java/util/logging/Logger:log	(Ljava/util/logging/Level;Ljava/lang/String;)V
    //   272: iinc 20 1
    //   275: lload 33
    //   277: lstore 17
    //   279: aload 39
    //   281: astore 19
    //   283: goto -142 -> 141
    //   286: iconst_0
    //   287: istore_1
    //   288: goto -276 -> 12
    //   291: aload_0
    //   292: getfield 22	att:a	Latj;
    //   295: getfield 70	atj:l	Ljava/util/concurrent/CompletionService;
    //   298: aload_0
    //   299: getfield 27	att:b	Latp;
    //   302: invokeinterface 76 2 0
    //   307: astore_2
    //   308: aload_2
    //   309: ldc2_w 161
    //   312: getstatic 115	java/util/concurrent/TimeUnit:MILLISECONDS	Ljava/util/concurrent/TimeUnit;
    //   315: invokeinterface 118 4 0
    //   320: checkcast 84	atq
    //   323: astore 7
    //   325: aload 7
    //   327: invokevirtual 121	atq:a	()Z
    //   330: ifne +6 -> 336
    //   333: aload 7
    //   335: areturn
    //   336: aload_0
    //   337: getfield 22	att:a	Latj;
    //   340: aload 7
    //   342: getfield 164	atq:b	Lauz;
    //   345: putfield 47	atj:d	Lauz;
    //   348: aload_0
    //   349: getfield 22	att:a	Latj;
    //   352: astore 8
    //   354: new 166	aua
    //   357: dup
    //   358: invokespecial 167	aua:<init>	()V
    //   361: astore 9
    //   363: aload 9
    //   365: aload_0
    //   366: getfield 22	att:a	Latj;
    //   369: getfield 47	atj:d	Lauz;
    //   372: getfield 170	auz:c	Ljava/lang/String;
    //   375: putfield 172	aua:a	Ljava/lang/String;
    //   378: aload 9
    //   380: aload_0
    //   381: getfield 22	att:a	Latj;
    //   384: getfield 47	atj:d	Lauz;
    //   387: getfield 54	auz:e	Lavk;
    //   390: getfield 174	avk:a	I
    //   393: aload_0
    //   394: getfield 22	att:a	Latj;
    //   397: getfield 47	atj:d	Lauz;
    //   400: getfield 54	auz:e	Lavk;
    //   403: getfield 175	avk:b	I
    //   406: invokevirtual 178	aua:a	(II)Laua;
    //   409: astore 10
    //   411: aload 10
    //   413: aload_0
    //   414: getfield 22	att:a	Latj;
    //   417: getfield 47	atj:d	Lauz;
    //   420: getfield 181	auz:j	I
    //   423: putfield 182	aua:b	I
    //   426: aload 8
    //   428: aload 10
    //   430: invokevirtual 185	aua:a	()Latz;
    //   433: putfield 189	atj:g	Latz;
    //   436: goto -403 -> 33
    //   439: astore 5
    //   441: getstatic 124	atj:a	Ljava/util/logging/Logger;
    //   444: getstatic 191	asn:a	Ljava/util/logging/Level;
    //   447: ldc 193
    //   449: aload 5
    //   451: invokevirtual 196	java/util/logging/Logger:log	(Ljava/util/logging/Level;Ljava/lang/String;Ljava/lang/Throwable;)V
    //   454: aload_2
    //   455: iconst_1
    //   456: invokeinterface 200 2 0
    //   461: pop
    //   462: new 84	atq
    //   465: dup
    //   466: bipush 102
    //   468: invokespecial 201	atq:<init>	(I)V
    //   471: areturn
    //   472: astore_3
    //   473: getstatic 124	atj:a	Ljava/util/logging/Logger;
    //   476: getstatic 191	asn:a	Ljava/util/logging/Level;
    //   479: ldc 203
    //   481: aload_3
    //   482: invokevirtual 196	java/util/logging/Logger:log	(Ljava/util/logging/Level;Ljava/lang/String;Ljava/lang/Throwable;)V
    //   485: aload_2
    //   486: iconst_1
    //   487: invokeinterface 200 2 0
    //   492: pop
    //   493: new 84	atq
    //   496: dup
    //   497: bipush 103
    //   499: invokespecial 201	atq:<init>	(I)V
    //   502: areturn
    //   503: astore 40
    //   505: invokestatic 91	android/os/SystemClock:uptimeMillis	()J
    //   508: lload 15
    //   510: lsub
    //   511: lstore 33
    //   513: getstatic 124	atj:a	Ljava/util/logging/Logger;
    //   516: astore 35
    //   518: getstatic 191	asn:a	Ljava/util/logging/Level;
    //   521: astore 36
    //   523: getstatic 135	java/util/Locale:US	Ljava/util/Locale;
    //   526: astore 37
    //   528: iconst_2
    //   529: anewarray 4	java/lang/Object
    //   532: astore 38
    //   534: aload 38
    //   536: iconst_0
    //   537: iload 20
    //   539: invokestatic 141	java/lang/Integer:valueOf	(I)Ljava/lang/Integer;
    //   542: aastore
    //   543: aload 38
    //   545: iconst_1
    //   546: lload 33
    //   548: invokestatic 146	java/lang/Long:valueOf	(J)Ljava/lang/Long;
    //   551: aastore
    //   552: aload 35
    //   554: aload 36
    //   556: aload 37
    //   558: ldc 205
    //   560: aload 38
    //   562: invokestatic 154	java/lang/String:format	(Ljava/util/Locale;Ljava/lang/String;[Ljava/lang/Object;)Ljava/lang/String;
    //   565: invokevirtual 160	java/util/logging/Logger:log	(Ljava/util/logging/Level;Ljava/lang/String;)V
    //   568: new 84	atq
    //   571: dup
    //   572: bipush 101
    //   574: invokespecial 201	atq:<init>	(I)V
    //   577: astore 39
    //   579: goto -307 -> 272
    //   582: astore 24
    //   584: getstatic 124	atj:a	Ljava/util/logging/Logger;
    //   587: getstatic 191	asn:a	Ljava/util/logging/Level;
    //   590: ldc 207
    //   592: aload 24
    //   594: invokevirtual 196	java/util/logging/Logger:log	(Ljava/util/logging/Level;Ljava/lang/String;Ljava/lang/Throwable;)V
    //   597: new 84	atq
    //   600: dup
    //   601: bipush 100
    //   603: invokespecial 201	atq:<init>	(I)V
    //   606: astore 19
    //   608: aload 11
    //   610: invokeinterface 211 1 0
    //   615: astore 25
    //   617: aload 25
    //   619: invokeinterface 216 1 0
    //   624: ifeq +217 -> 841
    //   627: aload 25
    //   629: invokeinterface 220 1 0
    //   634: checkcast 66	java/util/concurrent/Future
    //   637: iconst_1
    //   638: invokeinterface 200 2 0
    //   643: pop
    //   644: goto -27 -> 617
    //   647: aload 11
    //   649: invokeinterface 211 1 0
    //   654: astore 28
    //   656: aload 28
    //   658: invokeinterface 216 1 0
    //   663: ifeq +67 -> 730
    //   666: aload 28
    //   668: invokeinterface 220 1 0
    //   673: checkcast 66	java/util/concurrent/Future
    //   676: iconst_1
    //   677: invokeinterface 200 2 0
    //   682: pop
    //   683: goto -27 -> 656
    //   686: astore 21
    //   688: aload 11
    //   690: invokeinterface 211 1 0
    //   695: astore 22
    //   697: aload 22
    //   699: invokeinterface 216 1 0
    //   704: ifeq +23 -> 727
    //   707: aload 22
    //   709: invokeinterface 220 1 0
    //   714: checkcast 66	java/util/concurrent/Future
    //   717: iconst_1
    //   718: invokeinterface 200 2 0
    //   723: pop
    //   724: goto -27 -> 697
    //   727: aload 21
    //   729: athrow
    //   730: aload 19
    //   732: invokevirtual 121	atq:a	()Z
    //   735: ifeq +106 -> 841
    //   738: aload_0
    //   739: getfield 22	att:a	Latj;
    //   742: getfield 47	atj:d	Lauz;
    //   745: getfield 223	auz:f	Laug;
    //   748: ifnull +20 -> 768
    //   751: aload_0
    //   752: getfield 22	att:a	Latj;
    //   755: getfield 70	atj:l	Ljava/util/concurrent/CompletionService;
    //   758: aload_0
    //   759: getfield 33	att:e	Latr;
    //   762: invokeinterface 76 2 0
    //   767: pop
    //   768: aload_0
    //   769: getfield 22	att:a	Latj;
    //   772: getfield 227	atj:n	Ljava/util/concurrent/atomic/AtomicBoolean;
    //   775: iconst_1
    //   776: invokevirtual 233	java/util/concurrent/atomic/AtomicBoolean:set	(Z)V
    //   779: aload_0
    //   780: getfield 22	att:a	Latj;
    //   783: getfield 236	atj:e	Landroid/os/Handler;
    //   786: new 238	atu
    //   789: dup
    //   790: aload_0
    //   791: iload_1
    //   792: invokespecial 241	atu:<init>	(Latt;Z)V
    //   795: invokevirtual 247	android/os/Handler:post	(Ljava/lang/Runnable;)Z
    //   798: pop
    //   799: aload_0
    //   800: getfield 22	att:a	Latj;
    //   803: getfield 251	atj:k	Ljava/util/concurrent/Executor;
    //   806: new 253	ato
    //   809: dup
    //   810: aload_0
    //   811: getfield 22	att:a	Latj;
    //   814: invokespecial 256	ato:<init>	(Latj;)V
    //   817: invokeinterface 262 2 0
    //   822: aload 19
    //   824: areturn
    //   825: astore 32
    //   827: goto -322 -> 505
    //   830: astore_3
    //   831: goto -358 -> 473
    //   834: aload 19
    //   836: astore 39
    //   838: goto -629 -> 209
    //   841: aload 19
    //   843: areturn
    //
    // Exception table:
    //   from	to	target	type
    //   308	333	439	java/util/concurrent/TimeoutException
    //   336	436	439	java/util/concurrent/TimeoutException
    //   308	333	472	java/lang/InterruptedException
    //   336	436	472	java/lang/InterruptedException
    //   157	204	503	java/util/concurrent/ExecutionException
    //   141	150	582	java/lang/InterruptedException
    //   157	204	582	java/lang/InterruptedException
    //   209	272	582	java/lang/InterruptedException
    //   505	579	582	java/lang/InterruptedException
    //   141	150	686	finally
    //   157	204	686	finally
    //   209	272	686	finally
    //   505	579	686	finally
    //   584	608	686	finally
    //   157	204	825	java/util/concurrent/TimeoutException
    //   308	333	830	java/util/concurrent/ExecutionException
    //   336	436	830	java/util/concurrent/ExecutionException
  }
}

/* Location:           C:\Program Files\APK反编译\classes_dex2jar.jar
 * Qualified Name:     att
 * JD-Core Version:    0.6.0
 */