final class gf
  implements Runnable
{
  // ERROR //
  public final void run()
  {
    // Byte code:
    //   0: ldc 15
    //   2: invokestatic 21	java/security/MessageDigest:getInstance	(Ljava/lang/String;)Ljava/security/MessageDigest;
    //   5: putstatic 27	ge:a	Ljava/security/MessageDigest;
    //   8: getstatic 31	ge:b	Ljava/util/concurrent/CountDownLatch;
    //   11: invokevirtual 36	java/util/concurrent/CountDownLatch:countDown	()V
    //   14: return
    //   15: astore_2
    //   16: getstatic 31	ge:b	Ljava/util/concurrent/CountDownLatch;
    //   19: invokevirtual 36	java/util/concurrent/CountDownLatch:countDown	()V
    //   22: return
    //   23: astore_1
    //   24: getstatic 31	ge:b	Ljava/util/concurrent/CountDownLatch;
    //   27: invokevirtual 36	java/util/concurrent/CountDownLatch:countDown	()V
    //   30: aload_1
    //   31: athrow
    //
    // Exception table:
    //   from	to	target	type
    //   0	8	15	java/security/NoSuchAlgorithmException
    //   0	8	23	finally
  }
}

/* Location:           C:\Program Files\APK反编译\classes_dex2jar.jar
 * Qualified Name:     gf
 * JD-Core Version:    0.6.0
 */