package com.alipay.wandoujia;

final class cu
  implements Runnable
{
  cu(ct paramct, int paramInt1, ao paramao, String[] paramArrayOfString, String paramString, int paramInt2, f paramf)
  {
  }

  // ERROR //
  public final void run()
  {
    // Byte code:
    //   0: invokestatic 46	com/wandoujia/image/c/a:a	()Lcom/wandoujia/image/c/a;
    //   3: invokevirtual 49	com/wandoujia/image/c/a:b	()Landroid/content/Context;
    //   6: astore_1
    //   7: invokestatic 55	java/lang/System:currentTimeMillis	()J
    //   10: lstore 4
    //   12: sipush 1000
    //   15: aload_0
    //   16: getfield 25	com/alipay/wandoujia/cu:b	I
    //   19: imul
    //   20: i2l
    //   21: lstore 6
    //   23: new 57	java/lang/StringBuilder
    //   26: dup
    //   27: ldc 59
    //   29: invokespecial 62	java/lang/StringBuilder:<init>	(Ljava/lang/String;)V
    //   32: lload 6
    //   34: invokevirtual 66	java/lang/StringBuilder:append	(J)Ljava/lang/StringBuilder;
    //   37: ldc 68
    //   39: invokevirtual 71	java/lang/StringBuilder:append	(Ljava/lang/String;)Ljava/lang/StringBuilder;
    //   42: lload 4
    //   44: invokevirtual 66	java/lang/StringBuilder:append	(J)Ljava/lang/StringBuilder;
    //   47: pop
    //   48: invokestatic 75	android/support/v4/app/b:c	()V
    //   51: aload_0
    //   52: getfield 27	com/alipay/wandoujia/cu:c	Lcom/alipay/wandoujia/ao;
    //   55: aload_0
    //   56: getfield 23	com/alipay/wandoujia/cu:a	Lcom/alipay/wandoujia/ct;
    //   59: invokestatic 80	com/alipay/wandoujia/ct:b	(Lcom/alipay/wandoujia/ct;)Lcom/wandoujia/jupiter/notification/NotificationActionHandler;
    //   62: aload_0
    //   63: getfield 29	com/alipay/wandoujia/cu:d	[Ljava/lang/String;
    //   66: aload_0
    //   67: getfield 31	com/alipay/wandoujia/cu:e	Ljava/lang/String;
    //   70: aload_0
    //   71: getfield 33	com/alipay/wandoujia/cu:f	I
    //   74: aload_1
    //   75: lload 4
    //   77: lload 6
    //   79: aload_0
    //   80: getfield 35	com/alipay/wandoujia/cu:g	Lcom/alipay/wandoujia/f;
    //   83: invokestatic 83	com/alipay/wandoujia/ct:a	(Lcom/alipay/wandoujia/ao;Lcom/wandoujia/jupiter/notification/NotificationActionHandler;[Ljava/lang/String;Ljava/lang/String;ILandroid/content/Context;JJLcom/alipay/wandoujia/f;)V
    //   86: aload_0
    //   87: getfield 23	com/alipay/wandoujia/cu:a	Lcom/alipay/wandoujia/ct;
    //   90: invokestatic 86	com/alipay/wandoujia/ct:a	(Lcom/alipay/wandoujia/ct;)V
    //   93: return
    //   94: astore_3
    //   95: aload_0
    //   96: getfield 23	com/alipay/wandoujia/cu:a	Lcom/alipay/wandoujia/ct;
    //   99: invokestatic 86	com/alipay/wandoujia/ct:a	(Lcom/alipay/wandoujia/ct;)V
    //   102: return
    //   103: astore_2
    //   104: aload_0
    //   105: getfield 23	com/alipay/wandoujia/cu:a	Lcom/alipay/wandoujia/ct;
    //   108: invokestatic 86	com/alipay/wandoujia/ct:a	(Lcom/alipay/wandoujia/ct;)V
    //   111: aload_2
    //   112: athrow
    //
    // Exception table:
    //   from	to	target	type
    //   7	86	94	java/lang/Exception
    //   7	86	103	finally
  }
}

/* Location:           C:\WorkSpace\WandDouJiaNotificationBar\WanDou1.jar
 * Qualified Name:     com.alipay.wandoujia.cu
 * JD-Core Version:    0.6.0
 */