package com.alipay.wandoujia;

final class m
  implements Runnable
{
  m(l paraml)
  {
  }

  // ERROR //
  public final void run()
  {
    // Byte code:
    //   0: invokestatic 22	com/alipay/wandoujia/h:a	()V
    //   3: bipush 10
    //   5: invokestatic 28	android/os/Process:setThreadPriority	(I)V
    //   8: aload_0
    //   9: getfield 12	com/alipay/wandoujia/m:a	Lcom/alipay/wandoujia/l;
    //   12: invokevirtual 33	com/alipay/wandoujia/l:f	()V
    //   15: invokestatic 38	com/alipay/wandoujia/p:a	()Lcom/alipay/wandoujia/p;
    //   18: aload_0
    //   19: getfield 12	com/alipay/wandoujia/m:a	Lcom/alipay/wandoujia/l;
    //   22: invokevirtual 40	com/alipay/wandoujia/p:a	(Lcom/alipay/wandoujia/l;)V
    //   25: aload_0
    //   26: getfield 12	com/alipay/wandoujia/m:a	Lcom/alipay/wandoujia/l;
    //   29: invokestatic 43	com/alipay/wandoujia/l:a	(Lcom/alipay/wandoujia/l;)Ljava/lang/Object;
    //   32: astore 7
    //   34: aload 7
    //   36: monitorenter
    //   37: aload_0
    //   38: getfield 12	com/alipay/wandoujia/m:a	Lcom/alipay/wandoujia/l;
    //   41: invokestatic 46	com/alipay/wandoujia/l:b	(Lcom/alipay/wandoujia/l;)V
    //   44: aload 7
    //   46: monitorexit
    //   47: return
    //   48: astore 4
    //   50: aload 4
    //   52: invokestatic 51	android/support/v4/app/b:b	(Ljava/lang/Object;)V
    //   55: aload_0
    //   56: getfield 12	com/alipay/wandoujia/m:a	Lcom/alipay/wandoujia/l;
    //   59: invokestatic 43	com/alipay/wandoujia/l:a	(Lcom/alipay/wandoujia/l;)Ljava/lang/Object;
    //   62: astore 5
    //   64: aload 5
    //   66: monitorenter
    //   67: aload_0
    //   68: getfield 12	com/alipay/wandoujia/m:a	Lcom/alipay/wandoujia/l;
    //   71: invokestatic 46	com/alipay/wandoujia/l:b	(Lcom/alipay/wandoujia/l;)V
    //   74: aload 5
    //   76: monitorexit
    //   77: return
    //   78: astore 6
    //   80: aload 5
    //   82: monitorexit
    //   83: aload 6
    //   85: athrow
    //   86: astore_1
    //   87: aload_0
    //   88: getfield 12	com/alipay/wandoujia/m:a	Lcom/alipay/wandoujia/l;
    //   91: invokestatic 43	com/alipay/wandoujia/l:a	(Lcom/alipay/wandoujia/l;)Ljava/lang/Object;
    //   94: astore_2
    //   95: aload_2
    //   96: monitorenter
    //   97: aload_0
    //   98: getfield 12	com/alipay/wandoujia/m:a	Lcom/alipay/wandoujia/l;
    //   101: invokestatic 46	com/alipay/wandoujia/l:b	(Lcom/alipay/wandoujia/l;)V
    //   104: aload_2
    //   105: monitorexit
    //   106: aload_1
    //   107: athrow
    //   108: astore_3
    //   109: aload_2
    //   110: monitorexit
    //   111: aload_3
    //   112: athrow
    //   113: astore 8
    //   115: aload 7
    //   117: monitorexit
    //   118: aload 8
    //   120: athrow
    //
    // Exception table:
    //   from	to	target	type
    //   0	25	48	java/lang/Exception
    //   67	77	78	finally
    //   80	83	78	finally
    //   0	25	86	finally
    //   50	55	86	finally
    //   97	106	108	finally
    //   109	111	108	finally
    //   37	47	113	finally
    //   115	118	113	finally
  }
}

/* Location:           C:\WorkSpace\WandDouJiaNotificationBar\WanDou1.jar
 * Qualified Name:     com.alipay.wandoujia.m
 * JD-Core Version:    0.6.0
 */