package com.google.android.gms.ads.internal.request;

import java.io.OutputStream;

final class ac
  implements Runnable
{
  ac(LargeParcelTeleporter paramLargeParcelTeleporter, OutputStream paramOutputStream, byte[] paramArrayOfByte)
  {
  }

  // ERROR //
  public final void run()
  {
    // Byte code:
    //   0: new 24	java/io/DataOutputStream
    //   3: dup
    //   4: aload_0
    //   5: getfield 14	com/google/android/gms/ads/internal/request/ac:a	Ljava/io/OutputStream;
    //   8: invokespecial 27	java/io/DataOutputStream:<init>	(Ljava/io/OutputStream;)V
    //   11: astore_1
    //   12: aload_1
    //   13: aload_0
    //   14: getfield 16	com/google/android/gms/ads/internal/request/ac:b	[B
    //   17: arraylength
    //   18: invokevirtual 31	java/io/DataOutputStream:writeInt	(I)V
    //   21: aload_1
    //   22: aload_0
    //   23: getfield 16	com/google/android/gms/ads/internal/request/ac:b	[B
    //   26: invokevirtual 35	java/io/DataOutputStream:write	([B)V
    //   29: aload_1
    //   30: invokestatic 40	aop:a	(Ljava/io/Closeable;)V
    //   33: return
    //   34: astore_2
    //   35: aconst_null
    //   36: astore_1
    //   37: ldc 42
    //   39: aload_2
    //   40: invokestatic 47	com/google/android/gms/ads/internal/util/c:b	(Ljava/lang/String;Ljava/lang/Throwable;)V
    //   43: invokestatic 52	com/google/android/gms/ads/internal/bc:a	()Lcom/google/android/gms/ads/internal/bc;
    //   46: getfield 56	com/google/android/gms/ads/internal/bc:h	Lcom/google/android/gms/ads/internal/state/h;
    //   49: aload_2
    //   50: iconst_1
    //   51: invokevirtual 61	com/google/android/gms/ads/internal/state/h:a	(Ljava/lang/Throwable;Z)V
    //   54: aload_1
    //   55: ifnonnull +11 -> 66
    //   58: aload_0
    //   59: getfield 14	com/google/android/gms/ads/internal/request/ac:a	Ljava/io/OutputStream;
    //   62: invokestatic 40	aop:a	(Ljava/io/Closeable;)V
    //   65: return
    //   66: aload_1
    //   67: invokestatic 40	aop:a	(Ljava/io/Closeable;)V
    //   70: return
    //   71: astore_3
    //   72: aconst_null
    //   73: astore_1
    //   74: aload_1
    //   75: ifnonnull +12 -> 87
    //   78: aload_0
    //   79: getfield 14	com/google/android/gms/ads/internal/request/ac:a	Ljava/io/OutputStream;
    //   82: invokestatic 40	aop:a	(Ljava/io/Closeable;)V
    //   85: aload_3
    //   86: athrow
    //   87: aload_1
    //   88: invokestatic 40	aop:a	(Ljava/io/Closeable;)V
    //   91: goto -6 -> 85
    //   94: astore_3
    //   95: goto -21 -> 74
    //   98: astore_2
    //   99: goto -62 -> 37
    //
    // Exception table:
    //   from	to	target	type
    //   0	12	34	java/io/IOException
    //   0	12	71	finally
    //   12	29	94	finally
    //   37	54	94	finally
    //   12	29	98	java/io/IOException
  }
}

/* Location:           C:\Program Files\APK反编译\classes_dex2jar.jar
 * Qualified Name:     com.google.android.gms.ads.internal.request.ac
 * JD-Core Version:    0.6.0
 */