package com.wandoujia.p4.c;

final class b
  implements Runnable
{
  b(a parama, int paramInt1, boolean paramBoolean, int paramInt2, j paramj, String paramString)
  {
  }

  // ERROR //
  public final void run()
  {
    // Byte code:
    //   0: iconst_1
    //   1: istore_1
    //   2: aload_0
    //   3: getfield 23	com/wandoujia/p4/c/b:a	I
    //   6: ifne +392 -> 398
    //   9: aload_0
    //   10: getfield 25	com/wandoujia/p4/c/b:d	Z
    //   13: ifeq +385 -> 398
    //   16: aload_0
    //   17: getfield 21	com/wandoujia/p4/c/b:f	Lcom/wandoujia/p4/c/a;
    //   20: aload_0
    //   21: getfield 23	com/wandoujia/p4/c/b:a	I
    //   24: aload_0
    //   25: getfield 27	com/wandoujia/p4/c/b:b	I
    //   28: invokestatic 42	com/wandoujia/p4/c/a:a	(Lcom/wandoujia/p4/c/a;II)Ljava/util/List;
    //   31: astore 15
    //   33: aload 15
    //   35: invokeinterface 48 1 0
    //   40: aload_0
    //   41: getfield 27	com/wandoujia/p4/c/b:b	I
    //   44: if_icmpge +450 -> 494
    //   47: aload_0
    //   48: getfield 23	com/wandoujia/p4/c/b:a	I
    //   51: aload 15
    //   53: invokeinterface 48 1 0
    //   58: iadd
    //   59: istore 23
    //   61: aload_0
    //   62: getfield 27	com/wandoujia/p4/c/b:b	I
    //   65: aload 15
    //   67: invokeinterface 48 1 0
    //   72: isub
    //   73: istore 24
    //   75: aload_0
    //   76: getfield 21	com/wandoujia/p4/c/b:f	Lcom/wandoujia/p4/c/a;
    //   79: iload 23
    //   81: iload 24
    //   83: invokevirtual 51	com/wandoujia/p4/c/a:b	(II)Lcom/wandoujia/p4/c/k;
    //   86: astore 25
    //   88: aload 25
    //   90: ifnull +410 -> 500
    //   93: aload 25
    //   95: getfield 56	com/wandoujia/p4/c/k:a	Ljava/util/List;
    //   98: ifnull +402 -> 500
    //   101: aload 15
    //   103: aload 25
    //   105: getfield 56	com/wandoujia/p4/c/k:a	Ljava/util/List;
    //   108: invokeinterface 60 2 0
    //   113: pop
    //   114: goto +386 -> 500
    //   117: aload 15
    //   119: invokeinterface 64 1 0
    //   124: ifne +177 -> 301
    //   127: aload 16
    //   129: ifnonnull +139 -> 268
    //   132: new 53	com/wandoujia/p4/c/k
    //   135: dup
    //   136: aload 15
    //   138: aconst_null
    //   139: aconst_null
    //   140: invokespecial 67	com/wandoujia/p4/c/k:<init>	(Ljava/util/List;Ljava/lang/Long;Ljava/lang/Boolean;)V
    //   143: astore 17
    //   145: iconst_0
    //   146: istore_1
    //   147: aload_0
    //   148: getfield 29	com/wandoujia/p4/c/b:c	Lcom/wandoujia/p4/c/j;
    //   151: ifnull +24 -> 175
    //   154: aload_0
    //   155: getfield 21	com/wandoujia/p4/c/b:f	Lcom/wandoujia/p4/c/a;
    //   158: invokestatic 70	com/wandoujia/p4/c/a:a	(Lcom/wandoujia/p4/c/a;)Landroid/os/Handler;
    //   161: new 72	com/wandoujia/p4/c/c
    //   164: dup
    //   165: aload_0
    //   166: aload 17
    //   168: invokespecial 75	com/wandoujia/p4/c/c:<init>	(Lcom/wandoujia/p4/c/b;Lcom/wandoujia/p4/c/k;)V
    //   171: invokevirtual 81	android/os/Handler:post	(Ljava/lang/Runnable;)Z
    //   174: pop
    //   175: iload_1
    //   176: ifeq +48 -> 224
    //   179: aload_0
    //   180: getfield 21	com/wandoujia/p4/c/b:f	Lcom/wandoujia/p4/c/a;
    //   183: aload_0
    //   184: getfield 23	com/wandoujia/p4/c/b:a	I
    //   187: aload_0
    //   188: getfield 27	com/wandoujia/p4/c/b:b	I
    //   191: invokevirtual 84	com/wandoujia/p4/c/a:a	(II)Ljava/util/List;
    //   194: astore 20
    //   196: aload_0
    //   197: getfield 29	com/wandoujia/p4/c/b:c	Lcom/wandoujia/p4/c/j;
    //   200: ifnull +24 -> 224
    //   203: aload_0
    //   204: getfield 21	com/wandoujia/p4/c/b:f	Lcom/wandoujia/p4/c/a;
    //   207: invokestatic 70	com/wandoujia/p4/c/a:a	(Lcom/wandoujia/p4/c/a;)Landroid/os/Handler;
    //   210: new 86	com/wandoujia/p4/c/d
    //   213: dup
    //   214: aload_0
    //   215: aload 20
    //   217: invokespecial 89	com/wandoujia/p4/c/d:<init>	(Lcom/wandoujia/p4/c/b;Ljava/util/List;)V
    //   220: invokevirtual 81	android/os/Handler:post	(Ljava/lang/Runnable;)Z
    //   223: pop
    //   224: aload_0
    //   225: getfield 21	com/wandoujia/p4/c/b:f	Lcom/wandoujia/p4/c/a;
    //   228: astore 9
    //   230: aload 9
    //   232: monitorenter
    //   233: aload_0
    //   234: getfield 21	com/wandoujia/p4/c/b:f	Lcom/wandoujia/p4/c/a;
    //   237: invokestatic 92	com/wandoujia/p4/c/a:b	(Lcom/wandoujia/p4/c/a;)Ljava/util/Set;
    //   240: aload_0
    //   241: getfield 31	com/wandoujia/p4/c/b:e	Ljava/lang/String;
    //   244: invokeinterface 98 2 0
    //   249: pop
    //   250: aload_0
    //   251: getfield 21	com/wandoujia/p4/c/b:f	Lcom/wandoujia/p4/c/a;
    //   254: invokestatic 100	com/wandoujia/p4/c/a:c	(Lcom/wandoujia/p4/c/a;)Ljava/util/Set;
    //   257: aload_0
    //   258: invokeinterface 98 2 0
    //   263: pop
    //   264: aload 9
    //   266: monitorexit
    //   267: return
    //   268: new 53	com/wandoujia/p4/c/k
    //   271: dup
    //   272: aload 15
    //   274: aload 16
    //   276: getfield 103	com/wandoujia/p4/c/k:b	Ljava/lang/Long;
    //   279: aload 16
    //   281: getfield 106	com/wandoujia/p4/c/k:c	Ljava/lang/Boolean;
    //   284: invokespecial 67	com/wandoujia/p4/c/k:<init>	(Ljava/util/List;Ljava/lang/Long;Ljava/lang/Boolean;)V
    //   287: astore 17
    //   289: aload 16
    //   291: getfield 106	com/wandoujia/p4/c/k:c	Ljava/lang/Boolean;
    //   294: invokevirtual 111	java/lang/Boolean:booleanValue	()Z
    //   297: istore_1
    //   298: goto -151 -> 147
    //   301: new 53	com/wandoujia/p4/c/k
    //   304: dup
    //   305: aconst_null
    //   306: lconst_0
    //   307: invokestatic 117	java/lang/Long:valueOf	(J)Ljava/lang/Long;
    //   310: iconst_1
    //   311: invokestatic 120	java/lang/Boolean:valueOf	(Z)Ljava/lang/Boolean;
    //   314: invokespecial 67	com/wandoujia/p4/c/k:<init>	(Ljava/util/List;Ljava/lang/Long;Ljava/lang/Boolean;)V
    //   317: astore 17
    //   319: goto -172 -> 147
    //   322: astore_2
    //   323: aload_0
    //   324: getfield 21	com/wandoujia/p4/c/b:f	Lcom/wandoujia/p4/c/a;
    //   327: astore_3
    //   328: aload_3
    //   329: monitorenter
    //   330: aload_0
    //   331: getfield 21	com/wandoujia/p4/c/b:f	Lcom/wandoujia/p4/c/a;
    //   334: invokestatic 92	com/wandoujia/p4/c/a:b	(Lcom/wandoujia/p4/c/a;)Ljava/util/Set;
    //   337: aload_0
    //   338: getfield 31	com/wandoujia/p4/c/b:e	Ljava/lang/String;
    //   341: invokeinterface 98 2 0
    //   346: pop
    //   347: aload_0
    //   348: getfield 21	com/wandoujia/p4/c/b:f	Lcom/wandoujia/p4/c/a;
    //   351: invokestatic 100	com/wandoujia/p4/c/a:c	(Lcom/wandoujia/p4/c/a;)Ljava/util/Set;
    //   354: aload_0
    //   355: invokeinterface 98 2 0
    //   360: pop
    //   361: aload_3
    //   362: monitorexit
    //   363: aload_2
    //   364: athrow
    //   365: astore 18
    //   367: aload_0
    //   368: getfield 29	com/wandoujia/p4/c/b:c	Lcom/wandoujia/p4/c/j;
    //   371: ifnull -147 -> 224
    //   374: aload_0
    //   375: getfield 21	com/wandoujia/p4/c/b:f	Lcom/wandoujia/p4/c/a;
    //   378: invokestatic 70	com/wandoujia/p4/c/a:a	(Lcom/wandoujia/p4/c/a;)Landroid/os/Handler;
    //   381: new 122	com/wandoujia/p4/c/e
    //   384: dup
    //   385: aload_0
    //   386: aload 18
    //   388: invokespecial 125	com/wandoujia/p4/c/e:<init>	(Lcom/wandoujia/p4/c/b;Ljava/util/concurrent/ExecutionException;)V
    //   391: invokevirtual 81	android/os/Handler:post	(Ljava/lang/Runnable;)Z
    //   394: pop
    //   395: goto -171 -> 224
    //   398: aload_0
    //   399: getfield 21	com/wandoujia/p4/c/b:f	Lcom/wandoujia/p4/c/a;
    //   402: aload_0
    //   403: getfield 23	com/wandoujia/p4/c/b:a	I
    //   406: aload_0
    //   407: getfield 27	com/wandoujia/p4/c/b:b	I
    //   410: invokevirtual 127	com/wandoujia/p4/c/a:d	(II)Ljava/util/List;
    //   413: astore 13
    //   415: aload_0
    //   416: getfield 29	com/wandoujia/p4/c/b:c	Lcom/wandoujia/p4/c/j;
    //   419: ifnull -195 -> 224
    //   422: aload_0
    //   423: getfield 21	com/wandoujia/p4/c/b:f	Lcom/wandoujia/p4/c/a;
    //   426: invokestatic 70	com/wandoujia/p4/c/a:a	(Lcom/wandoujia/p4/c/a;)Landroid/os/Handler;
    //   429: new 129	com/wandoujia/p4/c/f
    //   432: dup
    //   433: aload_0
    //   434: aload 13
    //   436: invokespecial 130	com/wandoujia/p4/c/f:<init>	(Lcom/wandoujia/p4/c/b;Ljava/util/List;)V
    //   439: invokevirtual 81	android/os/Handler:post	(Ljava/lang/Runnable;)Z
    //   442: pop
    //   443: goto -219 -> 224
    //   446: astore 7
    //   448: aload_0
    //   449: getfield 29	com/wandoujia/p4/c/b:c	Lcom/wandoujia/p4/c/j;
    //   452: ifnull -228 -> 224
    //   455: aload_0
    //   456: getfield 21	com/wandoujia/p4/c/b:f	Lcom/wandoujia/p4/c/a;
    //   459: invokestatic 70	com/wandoujia/p4/c/a:a	(Lcom/wandoujia/p4/c/a;)Landroid/os/Handler;
    //   462: new 132	com/wandoujia/p4/c/g
    //   465: dup
    //   466: aload_0
    //   467: aload 7
    //   469: invokespecial 133	com/wandoujia/p4/c/g:<init>	(Lcom/wandoujia/p4/c/b;Ljava/util/concurrent/ExecutionException;)V
    //   472: invokevirtual 81	android/os/Handler:post	(Ljava/lang/Runnable;)Z
    //   475: pop
    //   476: goto -252 -> 224
    //   479: astore 10
    //   481: aload 9
    //   483: monitorexit
    //   484: aload 10
    //   486: athrow
    //   487: astore 4
    //   489: aload_3
    //   490: monitorexit
    //   491: aload 4
    //   493: athrow
    //   494: aconst_null
    //   495: astore 16
    //   497: goto -380 -> 117
    //   500: aload 25
    //   502: astore 16
    //   504: goto -387 -> 117
    //
    // Exception table:
    //   from	to	target	type
    //   2	88	322	finally
    //   93	114	322	finally
    //   117	127	322	finally
    //   132	145	322	finally
    //   147	175	322	finally
    //   179	224	322	finally
    //   268	298	322	finally
    //   301	319	322	finally
    //   367	395	322	finally
    //   398	443	322	finally
    //   448	476	322	finally
    //   179	224	365	java/util/concurrent/ExecutionException
    //   398	443	446	java/util/concurrent/ExecutionException
    //   233	267	479	finally
    //   481	484	479	finally
    //   330	363	487	finally
    //   489	491	487	finally
  }
}

/* Location:           C:\WorkSpace\WandDouJiaNotificationBar\WanDou1.jar
 * Qualified Name:     com.wandoujia.p4.c.b
 * JD-Core Version:    0.6.0
 */