package com.unionpay.pboctransaction.simapdu;

final class c extends Thread
{
  c(a parama)
  {
  }

  // ERROR //
  public final void run()
  {
    // Byte code:
    //   0: aload_0
    //   1: invokespecial 18	java/lang/Thread:run	()V
    //   4: aload_0
    //   5: monitorenter
    //   6: aload_0
    //   7: ldc2_w 19
    //   10: invokevirtual 26	java/lang/Object:wait	(J)V
    //   13: aload_0
    //   14: monitorexit
    //   15: aload_0
    //   16: getfield 10	com/unionpay/pboctransaction/simapdu/c:a	Lcom/unionpay/pboctransaction/simapdu/a;
    //   19: astore_3
    //   20: aload_3
    //   21: monitorenter
    //   22: aload_0
    //   23: getfield 10	com/unionpay/pboctransaction/simapdu/c:a	Lcom/unionpay/pboctransaction/simapdu/a;
    //   26: invokevirtual 32	com/unionpay/pboctransaction/simapdu/a:e	()Z
    //   29: ifne +15 -> 44
    //   32: aload_0
    //   33: getfield 10	com/unionpay/pboctransaction/simapdu/c:a	Lcom/unionpay/pboctransaction/simapdu/a;
    //   36: invokestatic 36	com/unionpay/pboctransaction/simapdu/a:c	(Lcom/unionpay/pboctransaction/simapdu/a;)Landroid/os/Handler;
    //   39: iconst_2
    //   40: invokevirtual 42	android/os/Handler:sendEmptyMessage	(I)Z
    //   43: pop
    //   44: aload_3
    //   45: monitorexit
    //   46: return
    //   47: astore 6
    //   49: aload_0
    //   50: monitorexit
    //   51: aload 6
    //   53: athrow
    //   54: astore_1
    //   55: new 44	java/lang/StringBuilder
    //   58: dup
    //   59: invokespecial 45	java/lang/StringBuilder:<init>	()V
    //   62: aload_1
    //   63: invokevirtual 49	java/lang/InterruptedException:getMessage	()Ljava/lang/String;
    //   66: invokevirtual 53	java/lang/StringBuilder:append	(Ljava/lang/String;)Ljava/lang/StringBuilder;
    //   69: pop
    //   70: goto -55 -> 15
    //   73: astore 4
    //   75: aload_3
    //   76: monitorexit
    //   77: aload 4
    //   79: athrow
    //
    // Exception table:
    //   from	to	target	type
    //   6	15	47	finally
    //   4	6	54	java/lang/InterruptedException
    //   49	54	54	java/lang/InterruptedException
    //   22	44	73	finally
    //   44	46	73	finally
  }
}

/* Location:           C:\WorkSpace\WandDouJiaNotificationBar\WanDou1.jar
 * Qualified Name:     com.unionpay.pboctransaction.simapdu.c
 * JD-Core Version:    0.6.0
 */